{
  "title": "١١. الدَّرْسُ الْحَادِيَ عَشَرَ",
  "tuz": "11-dars",
  "sub": "Ranglar va jismoniy nuqsonlar",
  "page": 25,
  "sentences": [
    {
      "ar": "هُوَ أَزْهَرُ،",
      "tr": "U oq yuzlidir",
      "parts": [
        {
          "w": "هُوَ",
          "r": "mubtado",
          "rc": "tm",
          "e": "هُوَ — U - ega; bu token alohida mashq qilinishi uchun ajratildi.",
          "uz": "u"
        },
        {
          "w": "أَزْهَرُ",
          "r": "xabar",
          "rc": "tx",
          "e": "أَزْهَرُ — Oq yuzlidir - xabar; bu token alohida mashq qilinishi uchun ajratildi.",
          "uz": "oq yuzlidir"
        }
      ]
    },
    {
      "ar": "هُمْ زُهْرٌ،",
      "tr": "Ular oq yuzlidirlar",
      "parts": [
        {
          "w": "هُمْ",
          "r": "mubtado",
          "rc": "tm",
          "e": "هُمْ — Ular - ega; bu token alohida mashq qilinishi uchun ajratildi.",
          "uz": "ular"
        },
        {
          "w": "زُهْرٌ",
          "r": "xabar",
          "rc": "tx",
          "e": "زُهْرٌ — Oq yuzlidirlar - xabar; bu token alohida mashq qilinishi uchun ajratildi.",
          "uz": "oq yuzlidirlar"
        }
      ]
    },
    {
      "ar": "هِيَ زَهْرَاءُ،",
      "tr": "U (ayol) oq yuzlidir",
      "parts": [
        {
          "w": "هِيَ",
          "r": "mubtado",
          "rc": "tm",
          "e": "هِيَ — U - ega; bu token alohida mashq qilinishi uchun ajratildi.",
          "uz": "u (ayol)"
        },
        {
          "w": "زَهْرَاءُ",
          "r": "xabar",
          "rc": "tx",
          "e": "زَهْرَاءُ — Oq yuzlidir - xabar; bu token alohida mashq qilinishi uchun ajratildi.",
          "uz": "oq yuzlidir"
        }
      ]
    },
    {
      "ar": "هُنَّ زُهْرٌ،",
      "tr": "Ular (ayollar) oq yuzlidirlar",
      "parts": [
        {
          "w": "هُنَّ",
          "r": "mubtado",
          "rc": "tm",
          "e": "هُنَّ — Ular - ega; bu token alohida mashq qilinishi uchun ajratildi.",
          "uz": "ular (ayollar)"
        },
        {
          "w": "زُهْرٌ",
          "r": "xabar",
          "rc": "tx",
          "e": "زُهْرٌ — Oq yuzlidirlar - xabar; bu token alohida mashq qilinishi uchun ajratildi.",
          "uz": "oq yuzlidirlar"
        }
      ]
    },
    {
      "ar": "أَنْتَ أَسْمَرُ،",
      "tr": "Sen qora (bug'doy) yuzlisan",
      "parts": [
        {
          "w": "أَنْتَ",
          "r": "mubtado",
          "rc": "tm",
          "e": "أَنْتَ — Sen - ega; bu token alohida mashq qilinishi uchun ajratildi.",
          "uz": "sen"
        },
        {
          "w": "أَسْمَرُ",
          "r": "xabar",
          "rc": "tx",
          "e": "أَسْمَرُ — Qora yuzlisan - xabar; bu token alohida mashq qilinishi uchun ajratildi.",
          "uz": "qora yuzlidir"
        }
      ]
    },
    {
      "ar": "أَنْتُمْ سُمْرٌ،",
      "tr": "Sizlar qora yuzlisizlar",
      "parts": [
        {
          "w": "أَنْتُمْ",
          "r": "mubtado",
          "rc": "tm",
          "e": "أَنْتُمْ — Sizlar - ega; bu token alohida mashq qilinishi uchun ajratildi.",
          "uz": "sizlar"
        },
        {
          "w": "سُمْرٌ",
          "r": "xabar",
          "rc": "tx",
          "e": "سُمْرٌ — Qora yuzlisizlar - xabar; bu token alohida mashq qilinishi uchun ajratildi.",
          "uz": "qora yuzlidirlar"
        }
      ]
    },
    {
      "ar": "أَنْتِ خَرْسَاءُ،",
      "tr": "Sen (ayol) tilsizsan (soqovsan)",
      "parts": [
        {
          "w": "أَنْتِ",
          "r": "mubtado",
          "rc": "tm",
          "e": "أَنْتِ — Sen - ega; bu token alohida mashq qilinishi uchun ajratildi.",
          "uz": "sen"
        },
        {
          "w": "خَرْسَاءُ",
          "r": "xabar",
          "rc": "tx",
          "e": "خَرْسَاءُ — Tilsizsan - xabar; bu token alohida mashq qilinishi uchun ajratildi.",
          "uz": "tilsizdir"
        }
      ]
    },
    {
      "ar": "أَنْتُنَّ خُرْسٌ،",
      "tr": "Sizlar (ayollar) tilsizlarsiz",
      "parts": [
        {
          "w": "أَنْتُنَّ",
          "r": "mubtado",
          "rc": "tm",
          "e": "أَنْتُنَّ — Sizlar - ega; bu token alohida mashq qilinishi uchun ajratildi.",
          "uz": "sizlar (ayollar)"
        },
        {
          "w": "خُرْسٌ",
          "r": "xabar",
          "rc": "tx",
          "e": "خُرْسٌ — Tilsizlarsiz - xabar; bu token alohida mashq qilinishi uchun ajratildi.",
          "uz": "tilsizlardir"
        }
      ]
    },
    {
      "ar": "أَنَا أَشْقَرُ،",
      "tr": "Men qizil yuzliman",
      "parts": [
        {
          "w": "أَنَا",
          "r": "mubtado",
          "rc": "tm",
          "e": "أَنَا — Men - ega; bu token alohida mashq qilinishi uchun ajratildi.",
          "uz": "men"
        },
        {
          "w": "أَشْقَرُ",
          "r": "xabar",
          "rc": "tx",
          "e": "أَشْقَرُ — Qizil yuzliman - xabar; bu token alohida mashq qilinishi uchun ajratildi.",
          "uz": "qizil yuzlidir"
        }
      ]
    },
    {
      "ar": "نَحْنُ شُقْرٌ،",
      "tr": "Biz qizil yuzlilarmiz",
      "parts": [
        {
          "w": "نَحْنُ",
          "r": "mubtado",
          "rc": "tm",
          "e": "نَحْنُ — Biz - ega; bu token alohida mashq qilinishi uchun ajratildi.",
          "uz": "biz"
        },
        {
          "w": "شُقْرٌ",
          "r": "xabar",
          "rc": "tx",
          "e": "شُقْرٌ — Qizil yuzlilarmiz - xabar; bu token alohida mashq qilinishi uchun ajratildi.",
          "uz": "qizil yuzlidirlar"
        }
      ]
    },
    {
      "ar": "هُوَ أَصَمُّ،",
      "tr": "U kardir",
      "parts": [
        {
          "w": "هُوَ",
          "r": "mubtado",
          "rc": "tm",
          "e": "هُوَ — U - ega; bu token alohida mashq qilinishi uchun ajratildi.",
          "uz": "u"
        },
        {
          "w": "أَصَمُّ",
          "r": "xabar",
          "rc": "tx",
          "e": "أَصَمُّ — Kardir - xabar; bu token alohida mashq qilinishi uchun ajratildi.",
          "uz": "kardir"
        }
      ]
    },
    {
      "ar": "هُمْ صُمٌّ،",
      "tr": "Ular karlardir",
      "parts": [
        {
          "w": "هُمْ",
          "r": "mubtado",
          "rc": "tm",
          "e": "هُمْ — Ular - ega; bu token alohida mashq qilinishi uchun ajratildi.",
          "uz": "ular"
        },
        {
          "w": "صُمٌّ",
          "r": "xabar",
          "rc": "tx",
          "e": "صُمٌّ — Karlardir - xabar; bu token alohida mashq qilinishi uchun ajratildi.",
          "uz": "karlardir"
        }
      ]
    },
    {
      "ar": "هِيَ عَمْيَاءُ،",
      "tr": "U (ayol) ko'rdir",
      "parts": [
        {
          "w": "هِيَ",
          "r": "mubtado",
          "rc": "tm",
          "e": "هِيَ — U - ega; bu token alohida mashq qilinishi uchun ajratildi.",
          "uz": "u (ayol)"
        },
        {
          "w": "عَمْيَاءُ",
          "r": "xabar",
          "rc": "tx",
          "e": "عَمْيَاءُ — Ko'rdir - xabar; bu token alohida mashq qilinishi uchun ajratildi.",
          "uz": "ko'rdir"
        }
      ]
    },
    {
      "ar": "هُنَّ عُمْيٌ،",
      "tr": "Ular (ayollar) ko'rlardir",
      "parts": [
        {
          "w": "هُنَّ",
          "r": "mubtado",
          "rc": "tm",
          "e": "هُنَّ — Ular - ega; bu token alohida mashq qilinishi uchun ajratildi.",
          "uz": "ular (ayollar)"
        },
        {
          "w": "عُمْيٌ",
          "r": "xabar",
          "rc": "tx",
          "e": "عُمْيٌ — Ko'rlardir - xabar; bu token alohida mashq qilinishi uchun ajratildi.",
          "uz": "mening amakim"
        }
      ]
    },
    {
      "ar": "أَنَا حَوْلَاءُ،",
      "tr": "Men (ayol) g'ilayman (g'ilay ko'zliman)",
      "parts": [
        {
          "w": "أَنَا",
          "r": "mubtado",
          "rc": "tm",
          "e": "أَنَا — Men - ega; bu token alohida mashq qilinishi uchun ajratildi.",
          "uz": "men"
        },
        {
          "w": "حَوْلَاءُ",
          "r": "xabar",
          "rc": "tx",
          "e": "حَوْلَاءُ — G'ilayman - xabar; bu token alohida mashq qilinishi uchun ajratildi.",
          "uz": "g'ilayman"
        }
      ]
    },
    {
      "ar": "نَحْنُ حُولٌ،",
      "tr": "Biz g'ilaylarmiz",
      "parts": [
        {
          "w": "نَحْنُ",
          "r": "mubtado",
          "rc": "tm",
          "e": "نَحْنُ — Biz - ega; bu token alohida mashq qilinishi uchun ajratildi.",
          "uz": "biz"
        },
        {
          "w": "حُولٌ",
          "r": "xabar",
          "rc": "tx",
          "e": "حُولٌ — G'ilaylarmiz - xabar; bu token alohida mashq qilinishi uchun ajratildi.",
          "uz": "g'ilaylardir"
        }
      ]
    },
    {
      "ar": "هَذَا الرَّجُلُ أَحْمَقُ،",
      "tr": "Bu kishi ahmoqdir",
      "parts": [
        {
          "w": "هَذَا",
          "r": "mubtado",
          "rc": "tm",
          "e": "هَذَا — Bu kishi - ega; bu token alohida mashq qilinishi uchun ajratildi.",
          "uz": "bu"
        },
        {
          "w": "الرَّجُلُ",
          "r": "بدل أو عطف بيان",
          "rc": "tm",
          "e": "الرَّجُلُ oldingi ko'rsatish ismini izohlaydi; butun ibora mubtado vazifasida kelgan.",
          "uz": "kishi"
        },
        {
          "w": "أَحْمَقُ",
          "r": "xabar",
          "rc": "tx",
          "e": "أَحْمَقُ — Ahmoqdir - xabar; bu token alohida mashq qilinishi uchun ajratildi.",
          "uz": "ahmoqdir"
        }
      ]
    },
    {
      "ar": "هَذِهِ الْمَرْأَةُ حَمْقَاءُ،",
      "tr": "Bu ayol ahmoqdir",
      "parts": [
        {
          "w": "هَذِهِ",
          "r": "mubtado",
          "rc": "tm",
          "e": "هَذِهِ — Bu ayol - ega; bu token alohida mashq qilinishi uchun ajratildi.",
          "uz": "bu"
        },
        {
          "w": "الْمَرْأَةُ",
          "r": "بدل أو عطف بيان",
          "rc": "tm",
          "e": "الْمَرْأَةُ oldingi ko'rsatish ismini izohlaydi; butun ibora mubtado vazifasida kelgan.",
          "uz": "ayol"
        },
        {
          "w": "حَمْقَاءُ",
          "r": "xabar",
          "rc": "tx",
          "e": "حَمْقَاءُ — Ahmoqdir - xabar; bu token alohida mashq qilinishi uchun ajratildi.",
          "uz": "ahmoqdir"
        }
      ]
    },
    {
      "ar": "هَذَا الْإِنْسَانُ أَشَلُّ،",
      "tr": "Bu inson cho'loqdir",
      "parts": [
        {
          "w": "هَذَا",
          "r": "mubtado",
          "rc": "tm",
          "e": "هَذَا — Bu inson - ega; bu token alohida mashq qilinishi uchun ajratildi.",
          "uz": "bu"
        },
        {
          "w": "الْإِنْسَانُ",
          "r": "بدل أو عطف بيان",
          "rc": "tm",
          "e": "الْإِنْسَانُ oldingi ko'rsatish ismini izohlaydi; butun ibora mubtado vazifasida kelgan.",
          "uz": "inson"
        },
        {
          "w": "أَشَلُّ",
          "r": "xabar",
          "rc": "tx",
          "e": "أَشَلُّ — Cho'loqdir - xabar; bu token alohida mashq qilinishi uchun ajratildi.",
          "uz": "cho'loqdir"
        }
      ]
    },
    {
      "ar": "هَذَا الشَّيْخُ أَعْرَجُ،",
      "tr": "Bu qariya oqsoqdir",
      "parts": [
        {
          "w": "هَذَا",
          "r": "mubtado",
          "rc": "tm",
          "e": "هَذَا — Bu qariya - ega; bu token alohida mashq qilinishi uchun ajratildi.",
          "uz": "bu"
        },
        {
          "w": "الشَّيْخُ",
          "r": "بدل أو عطف بيان",
          "rc": "tm",
          "e": "الشَّيْخُ oldingi ko'rsatish ismini izohlaydi; butun ibora mubtado vazifasida kelgan.",
          "uz": "qariya"
        },
        {
          "w": "أَعْرَجُ",
          "r": "xabar",
          "rc": "tx",
          "e": "أَعْرَجُ — Oqsoqdir - xabar; bu token alohida mashq qilinishi uchun ajratildi.",
          "uz": "oqsoqdir"
        }
      ]
    },
    {
      "ar": "هَذِهِ الْعَجُوزُ حَدْبَاءُ،",
      "tr": "Bu kampir bukridir",
      "parts": [
        {
          "w": "هَذِهِ",
          "r": "mubtado",
          "rc": "tm",
          "e": "هَذِهِ — Bu kampir - ega; bu token alohida mashq qilinishi uchun ajratildi.",
          "uz": "bu"
        },
        {
          "w": "الْعَجُوزُ",
          "r": "بدل أو عطف بيان",
          "rc": "tm",
          "e": "الْعَجُوزُ oldingi ko'rsatish ismini izohlaydi; butun ibora mubtado vazifasida kelgan.",
          "uz": "kampir"
        },
        {
          "w": "حَدْبَاءُ",
          "r": "xabar",
          "rc": "tx",
          "e": "حَدْبَاءُ — Bukridir - xabar; bu token alohida mashq qilinishi uchun ajratildi.",
          "uz": "bukridir"
        }
      ]
    },
    {
      "ar": "ذَاكَ الشَّابُّ أَزْهَرُ،",
      "tr": "Anavi yigit oq yuzlidir",
      "parts": [
        {
          "w": "ذَاكَ",
          "r": "mubtado",
          "rc": "tm",
          "e": "ذَاكَ — Anavi yigit - ega; bu token alohida mashq qilinishi uchun ajratildi.",
          "uz": "anavi"
        },
        {
          "w": "الشَّابُّ",
          "r": "بدل أو عطف بيان",
          "rc": "tm",
          "e": "الشَّابُّ oldingi ko'rsatish ismini izohlaydi; butun ibora mubtado vazifasida kelgan.",
          "uz": "yigit"
        },
        {
          "w": "أَزْهَرُ",
          "r": "xabar",
          "rc": "tx",
          "e": "أَزْهَرُ — Oq yuzlidir - xabar; bu token alohida mashq qilinishi uchun ajratildi.",
          "uz": "oq yuzlidir"
        }
      ]
    },
    {
      "ar": "تِلْكَ الشَّابَّةُ شَلَّاءُ،",
      "tr": "Anavi yosh qiz cho'loqdir",
      "parts": [
        {
          "w": "تِلْكَ",
          "r": "mubtado",
          "rc": "tm",
          "e": "تِلْكَ — Anavi yosh qiz - ega; bu token alohida mashq qilinishi uchun ajratildi.",
          "uz": "anavi"
        },
        {
          "w": "الشَّابَّةُ",
          "r": "بدل أو عطف بيان",
          "rc": "tm",
          "e": "الشَّابَّةُ oldingi ko'rsatish ismini izohlaydi; butun ibora mubtado vazifasida kelgan.",
          "uz": "qiz"
        },
        {
          "w": "شَلَّاءُ",
          "r": "xabar",
          "rc": "tx",
          "e": "شَلَّاءُ — Cho'loqdir - xabar; bu token alohida mashq qilinishi uchun ajratildi.",
          "uz": "cho'loqdir"
        }
      ]
    },
    {
      "ar": "هَذَا الصَّبِيُّ أَلْتَغُ،",
      "tr": "Bu go'dak soqovdir (duduqdir)",
      "parts": [
        {
          "w": "هَذَا",
          "r": "mubtado",
          "rc": "tm",
          "e": "هَذَا — Bu go'dak - ega; bu token alohida mashq qilinishi uchun ajratildi.",
          "uz": "bu"
        },
        {
          "w": "الصَّبِيُّ",
          "r": "بدل أو عطف بيان",
          "rc": "tm",
          "e": "الصَّبِيُّ oldingi ko'rsatish ismini izohlaydi; butun ibora mubtado vazifasida kelgan.",
          "uz": "bola"
        },
        {
          "w": "أَلْتَغُ",
          "r": "xabar",
          "rc": "tx",
          "e": "أَلْتَغُ — Soqovdir - xabar; bu token alohida mashq qilinishi uchun ajratildi.",
          "uz": "soqovdir"
        }
      ]
    },
    {
      "ar": "هَذِهِ الصَّبِيَّةُ لَثْغَاءُ،",
      "tr": "Bu go'dak qiz soqovdir",
      "parts": [
        {
          "w": "هَذِهِ",
          "r": "mubtado",
          "rc": "tm",
          "e": "هَذِهِ — Bu go'dak qiz - ega; bu token alohida mashq qilinishi uchun ajratildi.",
          "uz": "bu"
        },
        {
          "w": "الصَّبِيَّةُ",
          "r": "بدل أو عطف بيان",
          "rc": "tm",
          "e": "الصَّبِيَّةُ oldingi ko'rsatish ismini izohlaydi; butun ibora mubtado vazifasida kelgan.",
          "uz": "qiz bola"
        },
        {
          "w": "لَثْغَاءُ",
          "r": "xabar",
          "rc": "tx",
          "e": "لَثْغَاءُ — Soqovdir - xabar; bu token alohida mashq qilinishi uchun ajratildi.",
          "uz": "soqovdir"
        }
      ]
    },
    {
      "ar": "ذَاكَ الْخَادِمُ أَحْمَقُ،",
      "tr": "Anavi xizmatchi ahmoqdir",
      "parts": [
        {
          "w": "ذَاكَ",
          "r": "mubtado",
          "rc": "tm",
          "e": "ذَاكَ — Anavi xizmatchi - ega; bu token alohida mashq qilinishi uchun ajratildi.",
          "uz": "anavi"
        },
        {
          "w": "الْخَادِمُ",
          "r": "بدل أو عطف بيان",
          "rc": "tm",
          "e": "الْخَادِمُ oldingi ko'rsatish ismini izohlaydi; butun ibora mubtado vazifasida kelgan.",
          "uz": "xizmatchi"
        },
        {
          "w": "أَحْمَقُ",
          "r": "xabar",
          "rc": "tx",
          "e": "أَحْمَقُ — Ahmoqdir - xabar; bu token alohida mashq qilinishi uchun ajratildi.",
          "uz": "ahmoqdir"
        }
      ]
    },
    {
      "ar": "تِلْكَ الْخَادِمَةُ حَمْقَاءُ،",
      "tr": "Anavi xizmatkor qiz ahmoqdir",
      "parts": [
        {
          "w": "تِلْكَ",
          "r": "mubtado",
          "rc": "tm",
          "e": "تِلْكَ — Anavi xizmatkor qiz - ega; bu token alohida mashq qilinishi uchun ajratildi.",
          "uz": "anavi"
        },
        {
          "w": "الْخَادِمَةُ",
          "r": "بدل أو عطف بيان",
          "rc": "tm",
          "e": "الْخَادِمَةُ oldingi ko'rsatish ismini izohlaydi; butun ibora mubtado vazifasida kelgan.",
          "uz": "xizmatchi ayol"
        },
        {
          "w": "حَمْقَاءُ",
          "r": "xabar",
          "rc": "tx",
          "e": "حَمْقَاءُ — Ahmoqdir - xabar; bu token alohida mashq qilinishi uchun ajratildi.",
          "uz": "ahmoqdir"
        }
      ]
    },
    {
      "ar": "صَدِيقُهُ أَزْهَرُ،",
      "tr": "Uning do'sti oq yuzlidir",
      "parts": [
        {
          "w": "صَدِيقُهُ",
          "r": "mubtado",
          "rc": "tm",
          "e": "صَدِيقُهُ — Uning do'sti - ega; bu token alohida mashq qilinishi uchun ajratildi.",
          "uz": "uning do'sti"
        },
        {
          "w": "أَزْهَرُ",
          "r": "xabar",
          "rc": "tx",
          "e": "أَزْهَرُ — Oq yuzlidir - xabar; bu token alohida mashq qilinishi uchun ajratildi.",
          "uz": "oq yuzlidir"
        }
      ]
    },
    {
      "ar": "صَدِيقَتُهَا زَهْرَاءُ،",
      "tr": "Uning (ayol) do'sti oq yuzlidir",
      "parts": [
        {
          "w": "صَدِيقَتُهَا",
          "r": "mubtado",
          "rc": "tm",
          "e": "صَدِيقَتُهَا — Uning do'sti - ega; bu token alohida mashq qilinishi uchun ajratildi.",
          "uz": "uning dugonasi"
        },
        {
          "w": "زَهْرَاءُ",
          "r": "xabar",
          "rc": "tx",
          "e": "زَهْرَاءُ — Oq yuzlidir - xabar; bu token alohida mashq qilinishi uchun ajratildi.",
          "uz": "oq yuzlidir"
        }
      ]
    },
    {
      "ar": "اِبْنُكَ أَسْمَرُ،",
      "tr": "Sening o'g'ling qora yuzlidir",
      "parts": [
        {
          "w": "اِبْنُكَ",
          "r": "mubtado",
          "rc": "tm",
          "e": "اِبْنُكَ — Sening o'g'ling - ega; bu token alohida mashq qilinishi uchun ajratildi.",
          "uz": "sening o'g'ling"
        },
        {
          "w": "أَسْمَرُ",
          "r": "xabar",
          "rc": "tx",
          "e": "أَسْمَرُ — Qora yuzlidir - xabar; bu token alohida mashq qilinishi uchun ajratildi.",
          "uz": "qora yuzlidir"
        }
      ]
    },
    {
      "ar": "اِبْنَتُكِ سَمْرَاءُ،",
      "tr": "Sening (ayol) qizing qora yuzlidir",
      "parts": [
        {
          "w": "اِبْنَتُكِ",
          "r": "mubtado",
          "rc": "tm",
          "e": "اِبْنَتُكِ — Sening qizing - ega; bu token alohida mashq qilinishi uchun ajratildi.",
          "uz": "qizing"
        },
        {
          "w": "سَمْرَاءُ",
          "r": "xabar",
          "rc": "tx",
          "e": "سَمْرَاءُ — Qora yuzlidir - xabar; bu token alohida mashq qilinishi uchun ajratildi.",
          "uz": "qora yuzlidir"
        }
      ]
    },
    {
      "ar": "خَادِمِي أَشْقَرُ،",
      "tr": "Mening xizmatchim qizil yuzliman (to'g'risi: yuzlidir)",
      "parts": [
        {
          "w": "خَادِمِي",
          "r": "mubtado",
          "rc": "tm",
          "e": "خَادِمِي — Mening xizmatchim - ega; bu token alohida mashq qilinishi uchun ajratildi.",
          "uz": "mening xizmatkorim"
        },
        {
          "w": "أَشْقَرُ",
          "r": "xabar",
          "rc": "tx",
          "e": "أَشْقَرُ — Qizil yuzlidir - xabar; bu token alohida mashq qilinishi uchun ajratildi.",
          "uz": "qizil yuzlidir"
        }
      ]
    },
    {
      "ar": "خَادِمَتِي شَقْرَاءُ،",
      "tr": "Mening xizmatkor qizim qizil yuzlidir",
      "parts": [
        {
          "w": "خَادِمَتِي",
          "r": "mubtado",
          "rc": "tm",
          "e": "خَادِمَتِي — Mening xizmatkor qizim - ega; bu token alohida mashq qilinishi uchun ajratildi.",
          "uz": "mening xizmatkor qizim"
        },
        {
          "w": "شَقْرَاءُ",
          "r": "xabar",
          "rc": "tx",
          "e": "شَقْرَاءُ — Qizil yuzlidir - xabar; bu token alohida mashq qilinishi uchun ajratildi.",
          "uz": "qizil yuzlidir"
        }
      ]
    },
    {
      "ar": "خَادِمُهُمْ أَخْرَسُ،",
      "tr": "Ularning xizmatchisi tilsizdir",
      "parts": [
        {
          "w": "خَادِمُهُمْ",
          "r": "mubtado",
          "rc": "tm",
          "e": "خَادِمُهُمْ — Ularning xizmatchisi - ega; bu token alohida mashq qilinishi uchun ajratildi.",
          "uz": "ularning xizmatchisi"
        },
        {
          "w": "أَخْرَسُ",
          "r": "xabar",
          "rc": "tx",
          "e": "أَخْرَسُ — Tilsizdir - xabar; bu token alohida mashq qilinishi uchun ajratildi.",
          "uz": "tilsizdir"
        }
      ]
    },
    {
      "ar": "خَادِمَتُكُمْ صَمَّاءُ،",
      "tr": "Sizlarning xizmatkor qizingiz kardir",
      "parts": [
        {
          "w": "خَادِمَتُكُمْ",
          "r": "mubtado",
          "rc": "tm",
          "e": "خَادِمَتُكُمْ — Sizlarning xizmatkor qizingiz - ega; bu token alohida mashq qilinishi uchun ajratildi.",
          "uz": "xizmatkor qizingiz"
        },
        {
          "w": "صَمَّاءُ",
          "r": "xabar",
          "rc": "tx",
          "e": "صَمَّاءُ — Kardir - xabar; bu token alohida mashq qilinishi uchun ajratildi.",
          "uz": "kardir"
        }
      ]
    },
    {
      "ar": "أَبُوهُ أَصَمُّ،",
      "tr": "Uning otasi kardir",
      "parts": [
        {
          "w": "أَبُوهُ",
          "r": "mubtado",
          "rc": "tm",
          "e": "أَبُوهُ — Uning otasi - ega; bu token alohida mashq qilinishi uchun ajratildi.",
          "uz": "otasi"
        },
        {
          "w": "أَصَمُّ",
          "r": "xabar",
          "rc": "tx",
          "e": "أَصَمُّ — Kardir - xabar; bu token alohida mashq qilinishi uchun ajratildi.",
          "uz": "kardir"
        }
      ]
    },
    {
      "ar": "أُمُّهُ عَمْيَاءُ،",
      "tr": "Uning onasi ko'rdir",
      "parts": [
        {
          "w": "أُمُّهُ",
          "r": "mubtado",
          "rc": "tm",
          "e": "أُمُّهُ — Uning onasi - ega; bu token alohida mashq qilinishi uchun ajratildi.",
          "uz": "uning onasi"
        },
        {
          "w": "عَمْيَاءُ",
          "r": "xabar",
          "rc": "tx",
          "e": "عَمْيَاءُ — Ko'rdir - xabar; bu token alohida mashq qilinishi uchun ajratildi.",
          "uz": "ko'rdir"
        }
      ]
    },
    {
      "ar": "اِبْنُكَ أَحْوَلُ،",
      "tr": "Sening o'g'ling g'ilaydir",
      "parts": [
        {
          "w": "اِبْنُكَ",
          "r": "mubtado",
          "rc": "tm",
          "e": "اِبْنُكَ — Sening o'g'ling - ega; bu token alohida mashq qilinishi uchun ajratildi.",
          "uz": "sening o'g'ling"
        },
        {
          "w": "أَحْوَلُ",
          "r": "xabar",
          "rc": "tx",
          "e": "أَحْوَلُ — G'ilaydir - xabar; bu token alohida mashq qilinishi uchun ajratildi.",
          "uz": "g'ilaydir"
        }
      ]
    },
    {
      "ar": "اِبْنَتُكِ شَلَّاءُ،",
      "tr": "Sening qizing cho'loqdir",
      "parts": [
        {
          "w": "اِبْنَتُكِ",
          "r": "mubtado",
          "rc": "tm",
          "e": "اِبْنَتُكِ — Sening qizing - ega; bu token alohida mashq qilinishi uchun ajratildi.",
          "uz": "qizing"
        },
        {
          "w": "شَلَّاءُ",
          "r": "xabar",
          "rc": "tx",
          "e": "شَلَّاءُ — Cho'loqdir - xabar; bu token alohida mashq qilinishi uchun ajratildi.",
          "uz": "cho'loqdir"
        }
      ]
    },
    {
      "ar": "أَخِي أَعْرَجُ،",
      "tr": "Mening akam (inim) oqsoqdir",
      "parts": [
        {
          "w": "أَخِي",
          "r": "mubtado",
          "rc": "tm",
          "e": "أَخِي — Mening akam - ega; bu token alohida mashq qilinishi uchun ajratildi.",
          "uz": "mening akam"
        },
        {
          "w": "أَعْرَجُ",
          "r": "xabar",
          "rc": "tx",
          "e": "أَعْرَجُ — Oqsoqdir - xabar; bu token alohida mashq qilinishi uchun ajratildi.",
          "uz": "oqsoqdir"
        }
      ]
    },
    {
      "ar": "أُخْتِي لَثْغَاءُ،",
      "tr": "Mening opam (singlim) soqovdir (duduqdir)",
      "parts": [
        {
          "w": "أُخْتِي",
          "r": "mubtado",
          "rc": "tm",
          "e": "أُخْتِي — Mening opang - ega; bu token alohida mashq qilinishi uchun ajratildi.",
          "uz": "mening opam/singlim"
        },
        {
          "w": "لَثْغَاءُ",
          "r": "xabar",
          "rc": "tx",
          "e": "لَثْغَاءُ — Soqovdir - xabar; bu token alohida mashq qilinishi uchun ajratildi.",
          "uz": "soqovdir"
        }
      ]
    },
    {
      "ar": "صَدِيقُ عَلِيٍّ أَخْرَسُ،",
      "tr": "Alining do'sti tilsizdir",
      "parts": [
        {
          "w": "صَدِيقُ",
          "r": "mubtado",
          "rc": "tm",
          "e": "صَدِيقُ — Alining do'sti - ega; bu token alohida mashq qilinishi uchun ajratildi.",
          "uz": "do‘st"
        },
        {
          "w": "عَلِيٍّ",
          "r": "بدل أو عطف بيان",
          "rc": "tm",
          "e": "عَلِيٍّ oldingi ko'rsatish ismini izohlaydi; butun ibora mubtado vazifasida kelgan.",
          "uz": "Ali"
        },
        {
          "w": "أَخْرَسُ",
          "r": "xabar",
          "rc": "tx",
          "e": "أَخْرَسُ — Tilsizdir - xabar; bu token alohida mashq qilinishi uchun ajratildi.",
          "uz": "tilsizdir"
        }
      ]
    },
    {
      "ar": "صَدِيقَةُ مَرْيَمَ خَرْسَاءُ،",
      "tr": "Maryamning do'sti tilsizdir",
      "parts": [
        {
          "w": "صَدِيقَةُ",
          "r": "mubtado",
          "rc": "tm",
          "e": "صَدِيقَةُ — Maryamning do'sti - ega; bu token alohida mashq qilinishi uchun ajratildi.",
          "uz": "Maryamning"
        },
        {
          "w": "مَرْيَمَ",
          "r": "بدل أو عطف بيان",
          "rc": "tm",
          "e": "مَرْيَمَ oldingi ko'rsatish ismini izohlaydi; butun ibora mubtado vazifasida kelgan.",
          "uz": "Maryam"
        },
        {
          "w": "خَرْسَاءُ",
          "r": "xabar",
          "rc": "tx",
          "e": "خَرْسَاءُ — Tilsizdir - xabar; bu token alohida mashq qilinishi uchun ajratildi.",
          "uz": "tilsizdir"
        }
      ]
    },
    {
      "ar": "عَدُوُّ عَلِيٍّ أَصَمُّ،",
      "tr": "Alining dushmani kardir",
      "parts": [
        {
          "w": "عَدُوُّ",
          "r": "mubtado",
          "rc": "tm",
          "e": "عَدُوُّ — Alining dushmani - ega; bu token alohida mashq qilinishi uchun ajratildi.",
          "uz": "dushman"
        },
        {
          "w": "عَلِيٍّ",
          "r": "بدل أو عطف بيان",
          "rc": "tm",
          "e": "عَلِيٍّ oldingi ko'rsatish ismini izohlaydi; butun ibora mubtado vazifasida kelgan.",
          "uz": "Ali"
        },
        {
          "w": "أَصَمُّ",
          "r": "xabar",
          "rc": "tx",
          "e": "أَصَمُّ — Kardir - xabar; bu token alohida mashq qilinishi uchun ajratildi.",
          "uz": "kardir"
        }
      ]
    },
    {
      "ar": "عَدُوَّةُ زَيْنَبَ صَمَّاءُ،",
      "tr": "Zaynabning dushmani kardir",
      "parts": [
        {
          "w": "عَدُوَّةُ",
          "r": "mubtado",
          "rc": "tm",
          "e": "عَدُوَّةُ — Zaynabning dushmani - ega; bu token alohida mashq qilinishi uchun ajratildi.",
          "uz": "Zaynabning"
        },
        {
          "w": "زَيْنَبَ",
          "r": "بدل أو عطف بيان",
          "rc": "tm",
          "e": "زَيْنَبَ oldingi ko'rsatish ismini izohlaydi; butun ibora mubtado vazifasida kelgan.",
          "uz": "dushmani"
        },
        {
          "w": "صَمَّاءُ",
          "r": "xabar",
          "rc": "tx",
          "e": "صَمَّاءُ — Kardir - xabar; bu token alohida mashq qilinishi uchun ajratildi.",
          "uz": "kardir"
        }
      ]
    },
    {
      "ar": "جَارُ خَالِدٍ أَعْمَى،",
      "tr": "Xolidning qo'shnisi ko'rdir",
      "parts": [
        {
          "w": "جَارُ",
          "r": "mubtado",
          "rc": "tm",
          "e": "جَارُ — Xolidning qo'shnisi - ega; bu token alohida mashq qilinishi uchun ajratildi.",
          "uz": "qo‘shni"
        },
        {
          "w": "خَالِدٍ",
          "r": "بدل أو عطف بيان",
          "rc": "tm",
          "e": "خَالِدٍ oldingi ko'rsatish ismini izohlaydi; butun ibora mubtado vazifasida kelgan.",
          "uz": "Xolid"
        },
        {
          "w": "أَعْمَى",
          "r": "xabar",
          "rc": "tx",
          "e": "أَعْمَى — Ko'rdir - xabar; bu token alohida mashq qilinishi uchun ajratildi.",
          "uz": "ko'rdir"
        }
      ]
    },
    {
      "ar": "ضَيْفُ مَحْمُودٍ أَحْوَلُ،",
      "tr": "Mahmudning mehmoni g'ilaydir",
      "parts": [
        {
          "w": "ضَيْفُ",
          "r": "mubtado",
          "rc": "tm",
          "e": "ضَيْفُ — Mahmudning mehmoni - ega; bu token alohida mashq qilinishi uchun ajratildi.",
          "uz": "mehmon"
        },
        {
          "w": "مَحْمُودٍ",
          "r": "بدل أو عطف بيان",
          "rc": "tm",
          "e": "مَحْمُودٍ oldingi ko'rsatish ismini izohlaydi; butun ibora mubtado vazifasida kelgan.",
          "uz": "Mahmud"
        },
        {
          "w": "أَحْوَلُ",
          "r": "xabar",
          "rc": "tx",
          "e": "أَحْوَلُ — G'ilaydir - xabar; bu token alohida mashq qilinishi uchun ajratildi.",
          "uz": "g'ilaydir"
        }
      ]
    },
    {
      "ar": "أَبُو هَذَا الْخَيَّاطِ، أَشَلُّ،",
      "tr": "Bu tikuvchining onasi (to'g'risi: otasi) cho'loqdir",
      "parts": [
        {
          "w": "أَبُو",
          "r": "mubtado",
          "rc": "tm",
          "e": "أَبُو — Bu tikuvchining otasi - ega; bu token alohida mashq qilinishi uchun ajratildi.",
          "uz": "ota"
        },
        {
          "w": "هَذَا",
          "r": "بدل أو عطف بيان",
          "rc": "tm",
          "e": "هَذَا oldingi ko'rsatish ismini izohlaydi; butun ibora mubtado vazifasida kelgan.",
          "uz": "bu"
        },
        {
          "w": "الْخَيَّاطِ",
          "r": "بدل أو عطف بيان",
          "rc": "tm",
          "e": "الْخَيَّاطِ oldingi ko'rsatish ismini izohlaydi; butun ibora mubtado vazifasida kelgan.",
          "uz": "tikuvchi"
        },
        {
          "w": "أَشَلُّ",
          "r": "xabar",
          "rc": "tx",
          "e": "أَشَلُّ — Cho'loqdir - xabar; bu token alohida mashq qilinishi uchun ajratildi.",
          "uz": "cho'loqdir"
        }
      ]
    },
    {
      "ar": "أُمُّ هَذَا النَّجَّارِ، عَرْجَاءُ،",
      "tr": "Anavi duradgorning onasi qorayuzlidir (to'g'risi: Bu duradgorning onasi oqsoqdir)",
      "parts": [
        {
          "w": "أُمُّ",
          "r": "mubtado",
          "rc": "tm",
          "e": "أُمُّ — Bu duradgorning onasi - ega; bu token alohida mashq qilinishi uchun ajratildi.",
          "uz": "ona"
        },
        {
          "w": "هَذَا",
          "r": "بدل أو عطف بيان",
          "rc": "tm",
          "e": "هَذَا oldingi ko'rsatish ismini izohlaydi; butun ibora mubtado vazifasida kelgan.",
          "uz": "bu"
        },
        {
          "w": "النَّجَّارِ",
          "r": "بدل أو عطف بيان",
          "rc": "tm",
          "e": "النَّجَّارِ oldingi ko'rsatish ismini izohlaydi; butun ibora mubtado vazifasida kelgan.",
          "uz": "duradgor"
        },
        {
          "w": "عَرْجَاءُ",
          "r": "xabar",
          "rc": "tx",
          "e": "عَرْجَاءُ — Oqsoqdir - xabar; bu token alohida mashq qilinishi uchun ajratildi.",
          "uz": "oqsoqdir"
        }
      ]
    },
    {
      "ar": "اِبْنُ هَذَا الْحَدَّادِ ، أَحْدَبُ،",
      "tr": "Bu temirchining o'g'li bukridir",
      "parts": [
        {
          "w": "اِبْنُ",
          "r": "mubtado",
          "rc": "tm",
          "e": "اِبْنُ — Bu temirchining o'g'li - ega; bu token alohida mashq qilinishi uchun ajratildi.",
          "uz": "o‘g‘il"
        },
        {
          "w": "هَذَا",
          "r": "بدل أو عطف بيان",
          "rc": "tm",
          "e": "هَذَا oldingi ko'rsatish ismini izohlaydi; butun ibora mubtado vazifasida kelgan.",
          "uz": "bu"
        },
        {
          "w": "الْحَدَّادِ",
          "r": "بدل أو عطف بيان",
          "rc": "tm",
          "e": "الْحَدَّادِ oldingi ko'rsatish ismini izohlaydi; butun ibora mubtado vazifasida kelgan.",
          "uz": "temirchi"
        },
        {
          "w": "أَحْدَبُ",
          "r": "xabar",
          "rc": "tx",
          "e": "أَحْدَبُ — Bukridir - xabar; bu token alohida mashq qilinishi uchun ajratildi.",
          "uz": "bukridir"
        }
      ]
    },
    {
      "ar": "اِبْنَةُ هَذَا الْخَبَّازِ حَدْبَاءُ،",
      "tr": "Bu nonvoyning qizi bukridir",
      "parts": [
        {
          "w": "اِبْنَةُ",
          "r": "mubtado",
          "rc": "tm",
          "e": "اِبْنَةُ — Bu nonvoyning qizi - ega; bu token alohida mashq qilinishi uchun ajratildi.",
          "uz": "Bu"
        },
        {
          "w": "هَذَا",
          "r": "بدل أو عطف بيان",
          "rc": "tm",
          "e": "هَذَا oldingi ko'rsatish ismini izohlaydi; butun ibora mubtado vazifasida kelgan.",
          "uz": "bu"
        },
        {
          "w": "الْخَبَّازِ",
          "r": "بدل أو عطف بيان",
          "rc": "tm",
          "e": "الْخَبَّازِ oldingi ko'rsatish ismini izohlaydi; butun ibora mubtado vazifasida kelgan.",
          "uz": "nonvoy"
        },
        {
          "w": "حَدْبَاءُ",
          "r": "xabar",
          "rc": "tx",
          "e": "حَدْبَاءُ — Bukridir - xabar; bu token alohida mashq qilinishi uchun ajratildi.",
          "uz": "bukridir"
        }
      ]
    },
    {
      "ar": "أَخُو هَذَا الْقَصَّابِ، أَلْتَغُ،",
      "tr": "Bu qassobning akasi soqovdir",
      "parts": [
        {
          "w": "أَخُو",
          "r": "mubtado",
          "rc": "tm",
          "e": "أَخُو — Bu qassobning akasi - ega; bu token alohida mashq qilinishi uchun ajratildi.",
          "uz": "aka-uka"
        },
        {
          "w": "هَذَا",
          "r": "بدل أو عطف بيان",
          "rc": "tm",
          "e": "هَذَا oldingi ko'rsatish ismini izohlaydi; butun ibora mubtado vazifasida kelgan.",
          "uz": "bu"
        },
        {
          "w": "الْقَصَّابِ",
          "r": "بدل أو عطف بيان",
          "rc": "tm",
          "e": "الْقَصَّابِ oldingi ko'rsatish ismini izohlaydi; butun ibora mubtado vazifasida kelgan.",
          "uz": "akasi"
        },
        {
          "w": "أَلْتَغُ",
          "r": "xabar",
          "rc": "tx",
          "e": "أَلْتَغُ — Soqovdir - xabar; bu token alohida mashq qilinishi uchun ajratildi.",
          "uz": "soqovdir"
        }
      ]
    },
    {
      "ar": "أُخْتُ هَذَا الْخَفَّافِ، لَثْغَاءُ،",
      "tr": "Bu etikdo'zning singlisi soqovdir",
      "parts": [
        {
          "w": "أُخْتُ",
          "r": "mubtado",
          "rc": "tm",
          "e": "أُخْتُ — Bu etikdo'zning singlisi - ega; bu token alohida mashq qilinishi uchun ajratildi.",
          "uz": "opa-singil"
        },
        {
          "w": "هَذَا",
          "r": "بدل أو عطف بيان",
          "rc": "tm",
          "e": "هَذَا oldingi ko'rsatish ismini izohlaydi; butun ibora mubtado vazifasida kelgan.",
          "uz": "bu"
        },
        {
          "w": "الْخَفَّافِ",
          "r": "بدل أو عطف بيان",
          "rc": "tm",
          "e": "الْخَفَّافِ oldingi ko'rsatish ismini izohlaydi; butun ibora mubtado vazifasida kelgan.",
          "uz": "etikdo‘z"
        },
        {
          "w": "لَثْغَاءُ",
          "r": "xabar",
          "rc": "tx",
          "e": "لَثْغَاءُ — Soqovdir - xabar; bu token alohida mashq qilinishi uchun ajratildi.",
          "uz": "soqovdir"
        }
      ]
    },
    {
      "ar": "الرَّجُلُ الْأَخْرَسُ ، أَصَمُّ،",
      "tr": "Tilsiz kishi kardir",
      "parts": [
        {
          "w": "الرَّجُلُ",
          "r": "mubtado",
          "rc": "tm",
          "e": "الرَّجُلُ — Tilsiz kishi - ega; bu token alohida mashq qilinishi uchun ajratildi.",
          "uz": "kishi"
        },
        {
          "w": "الْأَخْرَسُ",
          "r": "بدل أو عطف بيان",
          "rc": "tm",
          "e": "الْأَخْرَسُ oldingi ko'rsatish ismini izohlaydi; butun ibora mubtado vazifasida kelgan.",
          "uz": "kishi"
        },
        {
          "w": "أَصَمُّ",
          "r": "xabar",
          "rc": "tx",
          "e": "أَصَمُّ — Kardir - xabar; bu token alohida mashq qilinishi uchun ajratildi.",
          "uz": "kardir"
        }
      ]
    },
    {
      "ar": "الرِّجَالُ الْخُرْسُ، صُمٌّ،",
      "tr": "Tilsiz kishilar karlardir",
      "parts": [
        {
          "w": "الرِّجَالُ",
          "r": "mubtado",
          "rc": "tm",
          "e": "الرِّجَالُ — Tilsiz kishilar - ega; bu token alohida mashq qilinishi uchun ajratildi.",
          "uz": "kishilar"
        },
        {
          "w": "الْخُرْسُ",
          "r": "بدل أو عطف بيان",
          "rc": "tm",
          "e": "الْخُرْسُ oldingi ko'rsatish ismini izohlaydi; butun ibora mubtado vazifasida kelgan.",
          "uz": "kishilar"
        },
        {
          "w": "صُمٌّ",
          "r": "xabar",
          "rc": "tx",
          "e": "صُمٌّ — Karlardir - xabar; bu token alohida mashq qilinishi uchun ajratildi.",
          "uz": "karlardir"
        }
      ]
    },
    {
      "ar": "الْمَرْأَةُ الْخَرْسَاءُ صَمَّاءُ،",
      "tr": "Tilsiz ayol kardir",
      "parts": [
        {
          "w": "الْمَرْأَةُ",
          "r": "mubtado",
          "rc": "tm",
          "e": "الْمَرْأَةُ — Tilsiz ayol - ega; bu token alohida mashq qilinishi uchun ajratildi.",
          "uz": "Tilsiz"
        },
        {
          "w": "الْخَرْسَاءُ",
          "r": "بدل أو عطف بيان",
          "rc": "tm",
          "e": "الْخَرْسَاءُ oldingi ko'rsatish ismini izohlaydi; butun ibora mubtado vazifasida kelgan.",
          "uz": "ayol"
        },
        {
          "w": "صَمَّاءُ",
          "r": "xabar",
          "rc": "tx",
          "e": "صَمَّاءُ — Kardir - xabar; bu token alohida mashq qilinishi uchun ajratildi.",
          "uz": "kardir"
        }
      ]
    },
    {
      "ar": "النِّسَاءُ الْخُرْسُ صُمٌّ،",
      "tr": "Tilsiz ayollar karlardir",
      "parts": [
        {
          "w": "النِّسَاءُ",
          "r": "mubtado",
          "rc": "tm",
          "e": "النِّسَاءُ — Tilsiz ayollar - ega; bu token alohida mashq qilinishi uchun ajratildi.",
          "uz": "ayollar"
        },
        {
          "w": "الْخُرْسُ",
          "r": "بدل أو عطف بيان",
          "rc": "tm",
          "e": "الْخُرْسُ oldingi ko'rsatish ismini izohlaydi; butun ibora mubtado vazifasida kelgan.",
          "uz": "ayollar"
        },
        {
          "w": "صُمٌّ",
          "r": "xabar",
          "rc": "tx",
          "e": "صُمٌّ — Karlardir - xabar; bu token alohida mashq qilinishi uchun ajratildi.",
          "uz": "karlardir"
        }
      ]
    },
    {
      "ar": "الْإِنْسَانُ الْأَعْمَى، مَحْزُونٌ،",
      "tr": "Ko'r inson xafadir (mahzundur)",
      "parts": [
        {
          "w": "الْإِنْسَانُ",
          "r": "mubtado",
          "rc": "tm",
          "e": "الْإِنْسَانُ — Ko'r inson - ega; bu token alohida mashq qilinishi uchun ajratildi.",
          "uz": "inson"
        },
        {
          "w": "الْأَعْمَى",
          "r": "بدل أو عطف بيان",
          "rc": "tm",
          "e": "الْأَعْمَى oldingi ko'rsatish ismini izohlaydi; butun ibora mubtado vazifasida kelgan.",
          "uz": "inson"
        },
        {
          "w": "مَحْزُونٌ",
          "r": "xabar",
          "rc": "tx",
          "e": "مَحْزُونٌ — Xafadir - xabar; bu token alohida mashq qilinishi uchun ajratildi.",
          "uz": "xafa"
        }
      ]
    },
    {
      "ar": "الشَّيْخُ الْأَعْرَجُ ، ضَعِيفٌ،",
      "tr": "Oqsoq qariya kuchsizdir",
      "parts": [
        {
          "w": "الشَّيْخُ",
          "r": "mubtado",
          "rc": "tm",
          "e": "الشَّيْخُ — Oqsoq qariya - ega; bu token alohida mashq qilinishi uchun ajratildi.",
          "uz": "qariya"
        },
        {
          "w": "الْأَعْرَجُ",
          "r": "بدل أو عطف بيان",
          "rc": "tm",
          "e": "الْأَعْرَجُ oldingi ko'rsatish ismini izohlaydi; butun ibora mubtado vazifasida kelgan.",
          "uz": "qariya"
        },
        {
          "w": "ضَعِيفٌ",
          "r": "xabar",
          "rc": "tx",
          "e": "ضَعِيفٌ — Kuchsizdir - xabar; bu token alohida mashq qilinishi uchun ajratildi.",
          "uz": "kuchsiz"
        }
      ]
    },
    {
      "ar": "الْعَجُوزُ الْحَدْبَاءُ، مَرِيضَةٌ،",
      "tr": "Bukri kampir kasaldir (bemordir)",
      "parts": [
        {
          "w": "الْعَجُوزُ",
          "r": "mubtado",
          "rc": "tm",
          "e": "الْعَجُوزُ — Bukri kampir - ega; bu token alohida mashq qilinishi uchun ajratildi.",
          "uz": "kampir"
        },
        {
          "w": "الْحَدْبَاءُ",
          "r": "بدل أو عطف بيان",
          "rc": "tm",
          "e": "الْحَدْبَاءُ oldingi ko'rsatish ismini izohlaydi; butun ibora mubtado vazifasida kelgan.",
          "uz": "kampir"
        },
        {
          "w": "مَرِيضَةٌ",
          "r": "xabar",
          "rc": "tx",
          "e": "مَرِيضَةٌ — Kasaldir - xabar; bu token alohida mashq qilinishi uchun ajratildi.",
          "uz": "bemor (ayol)"
        }
      ]
    },
    {
      "ar": "الْوَلَدُ الْأَلْتَغُ، مَرِيضٌ،",
      "tr": "Soqov bola kasaldir",
      "parts": [
        {
          "w": "الْوَلَدُ",
          "r": "mubtado",
          "rc": "tm",
          "e": "الْوَلَدُ — Soqov bola - ega; bu token alohida mashq qilinishi uchun ajratildi.",
          "uz": "bola"
        },
        {
          "w": "الْأَلْتَغُ",
          "r": "بدل أو عطف بيان",
          "rc": "tm",
          "e": "الْأَلْتَغُ oldingi ko'rsatish ismini izohlaydi; butun ibora mubtado vazifasida kelgan.",
          "uz": "bola"
        },
        {
          "w": "مَرِيضٌ",
          "r": "xabar",
          "rc": "tx",
          "e": "مَرِيضٌ — Kasaldir - xabar; bu token alohida mashq qilinishi uchun ajratildi.",
          "uz": "kasal"
        }
      ]
    },
    {
      "ar": "هَذَا الشَّابُّ الْأَشْقَرُ ، خَيَّاطٌ مَاهِرٌ،",
      "tr": "Bu qizil yuzli yigit mohir tikuvchidir",
      "parts": [
        {
          "w": "هَذَا",
          "r": "mubtado",
          "rc": "tm",
          "e": "هَذَا — Bu qizil yuzli yigit - ega; bu token alohida mashq qilinishi uchun ajratildi.",
          "uz": "bu"
        },
        {
          "w": "الشَّابُّ",
          "r": "بدل أو عطف بيان",
          "rc": "tm",
          "e": "الشَّابُّ oldingi ko'rsatish ismini izohlaydi; butun ibora mubtado vazifasida kelgan.",
          "uz": "yigit"
        },
        {
          "w": "الْأَشْقَرُ",
          "r": "بدل أو عطف بيان",
          "rc": "tm",
          "e": "الْأَشْقَرُ oldingi ko'rsatish ismini izohlaydi; butun ibora mubtado vazifasida kelgan.",
          "uz": "yuzli"
        },
        {
          "w": "خَيَّاطٌ",
          "r": "xabar",
          "rc": "tx",
          "e": "خَيَّاطٌ — Mohir tikuvchidir - xabar; bu token alohida mashq qilinishi uchun ajratildi.",
          "uz": "tikuvchi"
        },
        {
          "w": "مَاهِرٌ",
          "r": "نعت مرفوع",
          "rc": "tx",
          "e": "مَاهِرٌ xabar tarkibidagi sifatlovchi bo'lib, oldingi ismning ma'nosini aniqlaydi.",
          "uz": "tikuvchidir"
        }
      ]
    },
    {
      "ar": "ذَاكَ النَّجَّارُ الْأَخْرَسُ، أَصَمُّ،",
      "tr": "Anavi tilsiz duradgor kardir",
      "parts": [
        {
          "w": "ذَاكَ",
          "r": "mubtado",
          "rc": "tm",
          "e": "ذَاكَ — Anavi tilsiz duradgor - ega; bu token alohida mashq qilinishi uchun ajratildi.",
          "uz": "anavi"
        },
        {
          "w": "النَّجَّارُ",
          "r": "بدل أو عطف بيان",
          "rc": "tm",
          "e": "النَّجَّارُ oldingi ko'rsatish ismini izohlaydi; butun ibora mubtado vazifasida kelgan.",
          "uz": "duradgor"
        },
        {
          "w": "الْأَخْرَسُ",
          "r": "بدل أو عطف بيان",
          "rc": "tm",
          "e": "الْأَخْرَسُ oldingi ko'rsatish ismini izohlaydi; butun ibora mubtado vazifasida kelgan.",
          "uz": "duradgor"
        },
        {
          "w": "أَصَمُّ",
          "r": "xabar",
          "rc": "tx",
          "e": "أَصَمُّ — Kardir - xabar; bu token alohida mashq qilinishi uchun ajratildi.",
          "uz": "kardir"
        }
      ]
    },
    {
      "ar": "هَؤُلَاءِ الْحَدَّادُونَ الْخُرْسُ، صُمٌّ،",
      "tr": "Bu tilsiz temirchilar karlardir",
      "parts": [
        {
          "w": "هَؤُلَاءِ",
          "r": "mubtado",
          "rc": "tm",
          "e": "هَؤُلَاءِ — Bu tilsiz temirchilar - ega; bu token alohida mashq qilinishi uchun ajratildi.",
          "uz": "bular"
        },
        {
          "w": "الْحَدَّادُونَ",
          "r": "بدل أو عطف بيان",
          "rc": "tm",
          "e": "الْحَدَّادُونَ oldingi ko'rsatish ismini izohlaydi; butun ibora mubtado vazifasida kelgan.",
          "uz": "tilsiz"
        },
        {
          "w": "الْخُرْسُ",
          "r": "بدل أو عطف بيان",
          "rc": "tm",
          "e": "الْخُرْسُ oldingi ko'rsatish ismini izohlaydi; butun ibora mubtado vazifasida kelgan.",
          "uz": "temirchilar"
        },
        {
          "w": "صُمٌّ",
          "r": "xabar",
          "rc": "tx",
          "e": "صُمٌّ — Karlardir - xabar; bu token alohida mashq qilinishi uchun ajratildi.",
          "uz": "karlardir"
        }
      ]
    },
    {
      "ar": "أُولَئِكَ الْحَمَّالُونَ الْفُقَرَاءُ، حُولٌ،",
      "tr": "Anavi kambag'al hammollar g'ilaylardir",
      "parts": [
        {
          "w": "أُولَئِكَ",
          "r": "mubtado",
          "rc": "tm",
          "e": "أُولَئِكَ — Anavi kambag'al hammollar - ega; bu token alohida mashq qilinishi uchun ajratildi.",
          "uz": "anavilar"
        },
        {
          "w": "الْحَمَّالُونَ",
          "r": "بدل أو عطف بيان",
          "rc": "tm",
          "e": "الْحَمَّالُونَ oldingi ko'rsatish ismini izohlaydi; butun ibora mubtado vazifasida kelgan.",
          "uz": "hammollar"
        },
        {
          "w": "الْفُقَرَاءُ",
          "r": "بدل أو عطف بيان",
          "rc": "tm",
          "e": "الْفُقَرَاءُ oldingi ko'rsatish ismini izohlaydi; butun ibora mubtado vazifasida kelgan.",
          "uz": "kambag‘allar"
        },
        {
          "w": "حُولٌ",
          "r": "xabar",
          "rc": "tx",
          "e": "حُولٌ — G'ilaylardir - xabar; bu token alohida mashq qilinishi uchun ajratildi.",
          "uz": "g'ilaylardir"
        }
      ]
    },
    {
      "ar": "هَذَا الْخَلَّاقُ النَّحِيفُ، أَعْرَجُ،",
      "tr": "Bu oriq sartarosh oqsoqdir",
      "parts": [
        {
          "w": "هَذَا",
          "r": "mubtado",
          "rc": "tm",
          "e": "هَذَا — Bu oriq sartarosh - ega; bu token alohida mashq qilinishi uchun ajratildi.",
          "uz": "bu"
        },
        {
          "w": "الْخَلَّاقُ",
          "r": "بدل أو عطف بيان",
          "rc": "tm",
          "e": "الْخَلَّاقُ oldingi ko'rsatish ismini izohlaydi; butun ibora mubtado vazifasida kelgan.",
          "uz": "oriq"
        },
        {
          "w": "النَّحِيفُ",
          "r": "بدل أو عطف بيان",
          "rc": "tm",
          "e": "النَّحِيفُ oldingi ko'rsatish ismini izohlaydi; butun ibora mubtado vazifasida kelgan.",
          "uz": "ozg‘in"
        },
        {
          "w": "أَعْرَجُ",
          "r": "xabar",
          "rc": "tx",
          "e": "أَعْرَجُ — Oqsoqdir - xabar; bu token alohida mashq qilinishi uchun ajratildi.",
          "uz": "oqsoqdir"
        }
      ]
    },
    {
      "ar": "ذَاكَ الدَّلَّالُ الْمَاهِرُ، أَشَلُّ،",
      "tr": "Anavi mohir dallol cho'loqdir",
      "parts": [
        {
          "w": "ذَاكَ",
          "r": "mubtado",
          "rc": "tm",
          "e": "ذَاكَ — Anavi mohir dallol - ega; bu token alohida mashq qilinishi uchun ajratildi.",
          "uz": "anavi"
        },
        {
          "w": "الدَّلَّالُ",
          "r": "بدل أو عطف بيان",
          "rc": "tm",
          "e": "الدَّلَّالُ oldingi ko'rsatish ismini izohlaydi; butun ibora mubtado vazifasida kelgan.",
          "uz": "dallol"
        },
        {
          "w": "الْمَاهِرُ",
          "r": "بدل أو عطف بيان",
          "rc": "tm",
          "e": "الْمَاهِرُ oldingi ko'rsatish ismini izohlaydi; butun ibora mubtado vazifasida kelgan.",
          "uz": "dallol"
        },
        {
          "w": "أَشَلُّ",
          "r": "xabar",
          "rc": "tx",
          "e": "أَشَلُّ — Cho'loqdir - xabar; bu token alohida mashq qilinishi uchun ajratildi.",
          "uz": "cho'loqdir"
        }
      ]
    },
    {
      "ar": "هَؤُلَاءِ الرِّجَالُ الْفُقَرَاءُ، خُرْسٌ،",
      "tr": "Bu kambag'al kishilar tilsizlardir",
      "parts": [
        {
          "w": "هَؤُلَاءِ",
          "r": "mubtado",
          "rc": "tm",
          "e": "هَؤُلَاءِ — Bu kambag'al kishilar - ega; bu token alohida mashq qilinishi uchun ajratildi.",
          "uz": "bular"
        },
        {
          "w": "الرِّجَالُ",
          "r": "بدل أو عطف بيان",
          "rc": "tm",
          "e": "الرِّجَالُ oldingi ko'rsatish ismini izohlaydi; butun ibora mubtado vazifasida kelgan.",
          "uz": "kishilar"
        },
        {
          "w": "الْفُقَرَاءُ",
          "r": "بدل أو عطف بيان",
          "rc": "tm",
          "e": "الْفُقَرَاءُ oldingi ko'rsatish ismini izohlaydi; butun ibora mubtado vazifasida kelgan.",
          "uz": "kambag‘allar"
        },
        {
          "w": "خُرْسٌ",
          "r": "xabar",
          "rc": "tx",
          "e": "خُرْسٌ — Tilsizlardir - xabar; bu token alohida mashq qilinishi uchun ajratildi.",
          "uz": "tilsizlardir"
        }
      ]
    },
    {
      "ar": "أُولَئِكَ النِّسَاءُ الْمَرِيضَاتُ، عُمْيٌ،",
      "tr": "Anavi kasal ayollar ko'rlardir",
      "parts": [
        {
          "w": "أُولَئِكَ",
          "r": "mubtado",
          "rc": "tm",
          "e": "أُولَئِكَ — Anavi kasal ayollar - ega; bu token alohida mashq qilinishi uchun ajratildi.",
          "uz": "anavilar"
        },
        {
          "w": "النِّسَاءُ",
          "r": "بدل أو عطف بيان",
          "rc": "tm",
          "e": "النِّسَاءُ oldingi ko'rsatish ismini izohlaydi; butun ibora mubtado vazifasida kelgan.",
          "uz": "ayollar"
        },
        {
          "w": "الْمَرِيضَاتُ",
          "r": "بدل أو عطف بيان",
          "rc": "tm",
          "e": "الْمَرِيضَاتُ oldingi ko'rsatish ismini izohlaydi; butun ibora mubtado vazifasida kelgan.",
          "uz": "ayollar"
        },
        {
          "w": "عُمْيٌ",
          "r": "xabar",
          "rc": "tx",
          "e": "عُمْيٌ — Ko'rlardir - xabar; bu token alohida mashq qilinishi uchun ajratildi.",
          "uz": "mening amakim"
        }
      ]
    },
    {
      "ar": "هَؤُلَاءِ الرِّجَالُ الْجُهَلَاءُ صُمٌّ،",
      "tr": "Bu nodon kishilar karlardir",
      "parts": [
        {
          "w": "هَؤُلَاءِ",
          "r": "mubtado",
          "rc": "tm",
          "e": "هَؤُلَاءِ — Bu nodon kishilar - ega; bu token alohida mashq qilinishi uchun ajratildi.",
          "uz": "bular"
        },
        {
          "w": "الرِّجَالُ",
          "r": "بدل أو عطف بيان",
          "rc": "tm",
          "e": "الرِّجَالُ oldingi ko'rsatish ismini izohlaydi; butun ibora mubtado vazifasida kelgan.",
          "uz": "kishilar"
        },
        {
          "w": "الْجُهَلَاءُ",
          "r": "بدل أو عطف بيان",
          "rc": "tm",
          "e": "الْجُهَلَاءُ oldingi ko'rsatish ismini izohlaydi; butun ibora mubtado vazifasida kelgan.",
          "uz": "johillar"
        },
        {
          "w": "صُمٌّ",
          "r": "xabar",
          "rc": "tx",
          "e": "صُمٌّ — Karlardir - xabar; bu token alohida mashq qilinishi uchun ajratildi.",
          "uz": "karlardir"
        }
      ]
    },
    {
      "ar": "أُولَئِكَ النِّسَاءُ الْجَاهِلَاتُ عُمْيٌ،",
      "tr": "Anavi nodon ayollar ko'rlardir",
      "parts": [
        {
          "w": "أُولَئِكَ",
          "r": "mubtado",
          "rc": "tm",
          "e": "أُولَئِكَ — Anavi nodon ayollar - ega; bu token alohida mashq qilinishi uchun ajratildi.",
          "uz": "anavilar"
        },
        {
          "w": "النِّسَاءُ",
          "r": "بدل أو عطف بيان",
          "rc": "tm",
          "e": "النِّسَاءُ oldingi ko'rsatish ismini izohlaydi; butun ibora mubtado vazifasida kelgan.",
          "uz": "ayollar"
        },
        {
          "w": "الْجَاهِلَاتُ",
          "r": "بدل أو عطف بيان",
          "rc": "tm",
          "e": "الْجَاهِلَاتُ oldingi ko'rsatish ismini izohlaydi; butun ibora mubtado vazifasida kelgan.",
          "uz": "ayollar"
        },
        {
          "w": "عُمْيٌ",
          "r": "xabar",
          "rc": "tx",
          "e": "عُمْيٌ — Ko'rlardir - xabar; bu token alohida mashq qilinishi uchun ajratildi.",
          "uz": "mening amakim"
        }
      ]
    },
    {
      "ar": "مُعَلِّمُوهُمْ زُهْرٌ،",
      "tr": "Ularning o'qituvchilari oq yuzlidirlar",
      "parts": [
        {
          "w": "مُعَلِّمُوهُمْ",
          "r": "mubtado",
          "rc": "tm",
          "e": "مُعَلِّمُوهُمْ — Ularning o'qituvchilari - ega; bu token alohida mashq qilinishi uchun ajratildi.",
          "uz": "ularning o'qituvchilari"
        },
        {
          "w": "زُهْرٌ",
          "r": "xabar",
          "rc": "tx",
          "e": "زُهْرٌ — Oq yuzlidirlar - xabar; bu token alohida mashq qilinishi uchun ajratildi.",
          "uz": "oq yuzlidirlar"
        }
      ]
    },
    {
      "ar": "مُدَرِّسُوكُمْ سُمْرٌ،",
      "tr": "Sizlarning mudarrislaringiz qora yuzlidirlar",
      "parts": [
        {
          "w": "مُدَرِّسُوكُمْ",
          "r": "mubtado",
          "rc": "tm",
          "e": "مُدَرِّسُوكُمْ — Sizlarning mudarrislaringiz - ega; bu token alohida mashq qilinishi uchun ajratildi.",
          "uz": "mudarrislaringiz"
        },
        {
          "w": "سُمْرٌ",
          "r": "xabar",
          "rc": "tx",
          "e": "سُمْرٌ — Qora yuzlidirlar - xabar; bu token alohida mashq qilinishi uchun ajratildi.",
          "uz": "qora yuzlidirlar"
        }
      ]
    },
    {
      "ar": "مُؤَذِّنُونَا شُقْرٌ،",
      "tr": "Bizning muazzinlarimiz qizil yuzlidirlar",
      "parts": [
        {
          "w": "مُؤَذِّنُونَا",
          "r": "mubtado",
          "rc": "tm",
          "e": "مُؤَذِّنُونَا — Bizning muazzinlarimiz - ega; bu token alohida mashq qilinishi uchun ajratildi.",
          "uz": "bizning muazzinlarimiz"
        },
        {
          "w": "شُقْرٌ",
          "r": "xabar",
          "rc": "tx",
          "e": "شُقْرٌ — Qizil yuzlidirlar - xabar; bu token alohida mashq qilinishi uchun ajratildi.",
          "uz": "qizil yuzlidirlar"
        }
      ]
    },
    {
      "ar": "فَرَّاشُنَا أَحْمَقُ،",
      "tr": "Mening farroshim (to'g'risi: Bizning farroshimiz) ahmoqdir",
      "parts": [
        {
          "w": "فَرَّاشُنَا",
          "r": "mubtado",
          "rc": "tm",
          "e": "فَرَّاشُنَا — Bizning farroshimiz - ega; bu token alohida mashq qilinishi uchun ajratildi.",
          "uz": "bizning farroshimiz"
        },
        {
          "w": "أَحْمَقُ",
          "r": "xabar",
          "rc": "tx",
          "e": "أَحْمَقُ — Ahmoqdir - xabar; bu token alohida mashq qilinishi uchun ajratildi.",
          "uz": "ahmoqdir"
        }
      ]
    }
  ],
  "bookId": "shifohiyya"
}
