{
  "وَأَرَادَ": "xohladi",
  "إِبْرَاهِيمُ": "Ibrohim",
  "اللَّهَ": "Alloh",
  "النَّاسَ": "odamlarni",
  "وَخَرَجَ": "chiqdi",
  "وَوَدَّعَ": "xayrlashdi",
  "وَقَصَدَ": "yo'l oldi",
  "هَاجَرُ": "Hojar",
  "وَكَانَتْ": "edi",
  "مَكَّةُ": "Makka",
  "وَوَصَلَ": "yetib keldi",
  "وَنَزَلَ": "turdi",
  "فِيهَا": "unga",
  "وَتَرَكَ": "qoldirdi",
  "هَاجَرَ": "Hojarni",
  "إِسْمَاعِيلَ": "Ismoilni",
  "قَالَتْ": "dedi",
  "هُنَا": "bu yerda",
  "مَاءٌ": "suv",
  "هَلْ": "mi",
  "اللَّهُ": "Alloh",
  "قَالَ": "dedi",
  "نَعَمْ": "ha",
  "إِذًا": "unda",
  "أَنْ": "-ni, -ishni",
  "يُسَافِرَ": "safar qiladi",
  "إِلَى": "-ga",
  "بَلَدٍ": "yurt",
  "آخَرَ": "boshqa",
  "وَيَعْبُdَ": "va ibodat qilishni",
  "فِي": "ichida",
  "هِ": "Uning, uni",
  "وَيَدْعُو": "duo qiladi",
  "اللَّهِ": "Alloh",
  "مِنْ": "-dan",
  "بَلَدِ": "yurt",
  "وَالِدَ": "otasini",
  "هُ": "Uning, uni",
  "وَ": "va",
  "مَعَ": "birga",
  "زَوْجُ": "xotini",
  "زَوْجَ": "xotini",
  "زَوْجَهُ": "xotini",
  "لَيْسَ": "yo'q, emas",
  "هَا": "uni, unda",
  "عُشْبٌ": "o't",
  "لَا": "yo'q, emas",
  "شَجَرٌ": "daraxt",
  "بِئْرٌ": "quduq",
  "نَهْرٌ": "daryo",
  "حَيَوَانٌ": "hayvon",
  "بَشَرٌ": "inson",
  "مَكَّةَ": "Makkaga",
  "وَلَدَ": "o'g'lini",
  "لَمَّا": "paytda, qachonki",
  "أَرَادَ": "xohladi",
  "يَذْهَبَ": "ketadi",
  "أَيْنَ": "qayerga",
  "يَا": "ey",
  "سَيِّدِ": "xo'jayin",
  "ي": "mening",
  "أَ": "-mi",
  "تَتْرُكُ": "tashlab ketadi",
  "نِي": "meni",
  "طَعَامٌ": "taom",
  "أَمَرَ": "buyurdi",
  "كَ": "seni, sening",
  "بِ": "-ni, bilan",
  "هَذَا": "bu",
  "يُضَيِّعُ": "zoye qiladi",
  "نَا": "bizni"
}
