{
  "title": "١٤ ـ رُؤْيَا إِبْرَاهِيمَ",
  "tuz": "Ibrohimning tushi",
  "sub": "Ibrohim tushida Ismoilni qurbon qilish buyuriladi",
  "page": 23,
  "sentences": [
    {
      "ar": "وَعَادَ إِبْرَاهِيمُ إِلَى مَكَّةَ بَعْدَ مُدَّةٍ.",
      "tr": "Ibrohim bir muddatdan keyin Makkaga qaytdi.",
      "parts": [
        {
          "w": "وَعَادَ",
          "r": "فِعل مَاضٍ",
          "rc": "tf",
          "e": "وَعَادَ o'tgan zamon fe'li bo'lib, gapning asosiy predikatini tashkil etadi. Vov harfi atf yoki ibtido uchun kelgan, عَادَ esa «qaytdi» ma'nosidagi sulосий fe'ldir. Undan keyingi إِبْرَاهِيمُ fo'il, إِلَى مَكَّةَ yo'nalish, بَعْدَ مُدَّةٍ vaqt zarfi sifatida shu fe'lga bog'lanadi.",
          "uz": "qaytdi"
        },
        {
          "w": "إِبْرَاهِيمُ",
          "r": "فَاعِل",
          "rc": "tm",
          "e": "إِبْرَاهِيمُ وَعَادَ fe'lining fo'ili bo'lib, raf' holatida kelgan. Arab grammatikasida fe'ldan keyin kelgan ma'rifa ism odatda fo'il hisoblanadi va doimo raf' holatida bo'ladi. Bu so'z qaytish harakatini bajargan shaxsni aniq ifodalaydi.",
          "uz": "Ibrohim"
        },
        {
          "w": "إِلَى مَكَّةَ",
          "r": "جَار وَمَجرُور",
          "rc": "tmt",
          "e": "إِلَى مَكَّةَ jar-majrur tarkibi bo'lib, وَعَادَ fe'liga mutaalliq. إِلَى intihoi g'oya ma'nosidagi harf jar bo'lib yo'nalishni bildiradi, مَكَّةَ esa gayr munsarif ism sifatida kasra o'rniga fatha qabul qilgan. Bu tarkib qaytishning qaysi manzilga bo'lganini belgilaydi.",
          "uz": "Makkaga"
        },
        {
          "w": "بَعْدَ مُدَّةٍ",
          "r": "ظَرف زَمَان",
          "rc": "th",
          "e": "بَعْدَ مُدَّةٍ vaqt zarfi bo'lib, وَعَادَ fe'liga mutaalliq zarfiy nasb holatida kelgan. بَعْدَ vaqt zarfi bo'lib, muzofilik uchun fathada, مُدَّةٍ esa muzofun ilayhi sifatida jarr holatida tanvini kasra bilan kelgan. Bu tarkib qaytish qachon sodir bo'lganini — muayyan muddat o'tgach — ko'rsatadi.",
          "uz": "bir muddatdan keyin"
        }
      ]
    },
    {
      "ar": "وَلَقِيَ إِسْمَاعِيلَ وَلَقِيَ هَاجَرَ، وَفَرِحَ إِبْرَاهِيمُ بِوَلَدِهِ إِسْمَاعِيلَ.",
      "tr": "Ismoil va Hojarni uchratdi. Ibrohim o'g'li Ismoil bilan xursand bo'ldi.",
      "parts": [
        {
          "w": "وَلَقِيَ",
          "r": "فِعل مَاضٍ",
          "rc": "tf",
          "e": "وَلَقِيَ o'tgan zamon fe'li bo'lib, yashirin fo'ili oldingi gapdan anglashilgan Ibrohim. لَقِيَ uchrashish, ko'rishish ma'nosidagi muta'addi fe'l bo'lib, o'zidan keyin nasb holatida maf'ul oladi. Birinchi uchrashuv shaxsi إِسْمَاعِيلَ ekanini keyingi maf'ul ko'rsatadi.",
          "uz": "uchratdi"
        },
        {
          "w": "إِسْمَاعِيلَ",
          "r": "مَفعُول بِه",
          "rc": "tb",
          "e": "إِسْمَاعِيلَ وَلَقِيَ fe'lining birinchi maf'uli bo'lib, nasb holatida kelgan. Ismning gayr munsarif ekani — ya'ni alam va a'jamiylik illatlarini o'z ichiga olishi — fathani nasb alomati sifatida qabul qilishiga sabab bo'lgan. Bu so'z Ibrohim uchratgan birinchi shaxsni ifodalaydi.",
          "uz": "Ismoilni"
        },
        {
          "w": "وَلَقِيَ",
          "r": "فِعل مَاضٍ",
          "rc": "tf",
          "e": "Ikkinchi وَلَقِيَ oldingi fe'lga vov atf bilan bog'langan mustaqil fe'l-jumla bo'lib, yashirin fo'ili yana Ibrohim. Birinchi uchrashuvga qo'shimcha holda ikkinchi uchrashuvni — bu safar Hojar bilan — ifodalaydi. Arab grammatikasida bir xil tuzilishdagi fe'llarning takrori rivoyatni ketma-ket ta'kidlash uchun qo'llaniladi.",
          "uz": "uchratdi"
        },
        {
          "w": "هَاجَرَ",
          "r": "مَفعُول بِه",
          "rc": "tb",
          "e": "هَاجَرَ ikkinchi وَلَقِيَ fe'lining maf'uli bo'lib, nasb holatida kelgan. Ismning gayr munsarif ekani fathadan nasb alomati sifatida foydalanilishini taqozo etgan. Bu so'z Ibrohim uchratgan ikkinchi shaxsni — Hojarni — belgilaydi.",
          "uz": "Hojarni"
        },
        {
          "w": "وَفَرِحَ",
          "r": "فِعل مَاضٍ",
          "rc": "tf",
          "e": "وَفَرِحَ yangi fe'l-jumlaning predikat fe'li bo'lib, vov atf bilan oldingi voqeaga ulangan. فَرِحَ his-tuyg'u ma'nosidagi lazim fe'l bo'lib, fo'ili keyingi إِبْرَاهِيمُ sifatida ochiq kelgan. Xursandlik sababi بِوَلَدِهِ jar-majruri orqali ifodalangan.",
          "uz": "xursand bo'ldi"
        },
        {
          "w": "بِوَلَدِهِ",
          "r": "جَار وَمَجرُور",
          "rc": "tmt",
          "e": "بِوَلَدِهِ jar-majrur tarkibi bo'lib, وَفَرِحَ fe'liga mutaalliq. بِ harfi jar bu yerda سَبَبِيَّة — sabablik ma'nosida ishlatilgan, وَلَدِهِ esa jarr holatida izofa tarkibida kelgan. Ondagi -هِ zamiri Ibrohimga qaytib, xursandlik sababining aynan uning farzandidan kelib chiqishini ko'rsatadi.",
          "uz": "o'g'lidan"
        },
        {
          "w": "إِسْمَاعِيلَ",
          "r": "بَدَل",
          "rc": "tb",
          "e": "إِسْمَاعِيلَ وَلَدِهِ so'zining badali bo'lib, o'rnini bosayotgan ism bilan grammatik muvofiqlikda turadi. Badal qoidasi bo'yicha majrur bo'lishi lozim, ammo gayr munsarif sifatida kasra o'rniga fatha bilan kelgan. «O'g'li» noaniq iborasini to'liq ism bilan oydinlashtiradi.",
          "uz": "Ismoilni"
        },
        {
          "w": "إِبْرَاهِيمُ",
          "r": "فَاعِل",
          "rc": "tb",
          "e": "إِبْرَاهِيمُ وَفَرِحَ fe'lining fo'ili bo'lib, raf' holatida kelgan. Arab grammatikasida fe'ldan keyin kelgan ochiq ism fo'il vazifasida bo'lib, har doim raf' holatida turadi. Bu so'z gapda xursandlik his-tuyg'usini boshdan kechirgan shaxsni aniq ifodalaydi.",
          "uz": "Ibrohim"
        }
      ]
    },
    {
      "ar": "وَكَانَ إِسْمَاعِيلُ وَلَدًا صَغِيرًا، يَجْرِي وَيَلْعَبُ وَيَخْرُجُ مَعَ وَالِدِهِ.",
      "tr": "Ismoil kichkina bola edi, yugurar, o'ynar va otasi bilan chiqardi.",
      "parts": [
        {
          "w": "وَكَانَ",
          "r": "فِعل مَاضٍ نَاقِص",
          "rc": "tf",
          "e": "وَكَانَ noqis o'tgan zamon fe'li bo'lib, ismi raf', xabarini nasb holatida boshqaradi. كانَ fe'li mustaqil ravishda to'liq gapning xulosasini bermaydi, balki ism va xabar o'rtasida vaqtiy-holat aloqasi o'rnatadi. Bu gap Ismoilning o'sha davrda kichkina bola ekanligini tavsiflovchi holat jumlasini hosil qiladi.",
          "uz": "edi"
        },
        {
          "w": "إِسْمَاعِيلُ",
          "r": "اسم كَان",
          "rc": "tm",
          "e": "إِسْمَاعِيلُ كانَning ismi bo'lib, raf' holatida kelgan. كانَ ismi doimo raf' holatida bo'ladi va gapning mavzuini belgilaydi. Bu yerda Ismoilning bolalik davridagi holi وَلَدًا صَغِيرًا xabari orqali bayon qilinmoqda.",
          "uz": "Ismoilni"
        },
        {
          "w": "وَلَدًا صَغِيرًا",
          "r": "خَبَر كَان",
          "rc": "tx",
          "e": "وَلَدًا صَغِيرًا كانَning xabari bo'lib, nasb holatida kelgan. وَلَدًا asosiy xabar, صَغِيرًا esa uning na'ti — sifati bo'lib, ikkalasi ham nasb alomati tanvini fathani qabul qilgan. Bu tarkib Ismoilning kichik yoshdagi holatini tasvirlaydi.",
          "uz": "kichkina bola"
        },
        {
          "w": "يَجْرِي",
          "r": "جُمْلَة حَالِيَّة",
          "rc": "th",
          "e": "يَجْرِي fe'l-jumlasi hol vazifasida bo'lib, إِسْمَاعِيلُning bolalik davridagi holatini tasvirlaydi. Hol sohibi — Ismoil, hol esa uning o'sha davrdagi faoliyatini ko'rsatadi. Muzore' shaklidagi bu fe'l holning davomiyligini va odatiyligini ifodalash uchun qo'llanilgan.",
          "uz": "yuguradi"
        },
        {
          "w": "وَيَلْعَبُ",
          "r": "مَعطُوف",
          "rc": "tb",
          "e": "وَيَلْعَبُ يَجْرِيga vov atf bilan bog'langan va u bilan bir xil grammatik vazifada — hol fe'l-jumlasi sifatida — turadi. Atf qoidasiga ko'ra ma'tuf ma'tufun alayh bilan muvofiq holatda bo'lishi lozim. Bu fe'l Ismoilning o'sha davrdagi yana bir doimiy mashg'ulotini — o'yinni — ko'rsatadi.",
          "uz": "o'ynaydi"
        },
        {
          "w": "وَيَخْرُجُ",
          "r": "مَعطُوف",
          "rc": "tb",
          "e": "وَيَخْرُجُ oldingi ikkala fe'lga vov atf bilan bog'langan uchinchi hol fe'li bo'lib, ular bilan bir xil grammatik vazifada turadi. يَجْرِي va يَلْعَبُga parallel kelishi bilan Ismoilning bolalikdagi hayot tarzi to'liq manzarasini chizadi. Bu fe'lning yashirin fo'ili ham Ismoilni anglatadi.",
          "uz": "chiqadi"
        },
        {
          "w": "مَعَ وَالِدِهِ",
          "r": "ظَرف مَكَان",
          "rc": "th",
          "e": "مَعَ وَالِدِهِ ma'iyyat zarfi bo'lib, وَيَخْرُجُ fe'liga mutaalliq. مَعَ birga bo'lish va hamrohlik ma'nosidagi zarf, وَالِدِهِ esa uning muzofun ilayhi bo'lib, jarr holatida kelgan. Ondagi -هِ zamiri Ismoilga qaytib, chiqish kimning hamrohligida bo'lganini ko'rsatadi.",
          "uz": "otasi bilan"
        }
      ]
    },
    {
      "ar": "وَكَانَ إِبْرَاهِيمُ يُحِبُّ إِسْمَاعِيلَ جِدًّا.",
      "tr": "Ibrohim Ismoilni juda yaxshi ko'rar edi.",
      "parts": [
        {
          "w": "وَكَانَ",
          "r": "فِعل مَاضٍ نَاقِص",
          "rc": "tf",
          "e": "وَكَانَ noqis o'tgan zamon fe'li bo'lib, ismi raf', xabarini nasb holatida boshqaradi. Bu yerda xabar fe'l-jumla shaklida kelgan — يُحِبُّ. كانَ Ibrohimning doimiy muhabbat holatini o'tmishda sodir bo'lgan davomiy jarayon sifatida ifodalaydi.",
          "uz": "edi"
        },
        {
          "w": "إِبْرَاهِيمُ",
          "r": "اسم كَان",
          "rc": "tm",
          "e": "إِبْرَاهِيمُ كانَning ismi bo'lib, raf' holatida kelgan. كانَ ismi bo'lgani uchun doimo raf' holatida turadi va gapning mavzuini belgilaydi. Keyingi يُحِبُّ fe'l-jumlasi aynan shu shaxs haqidagi xabarni beradi.",
          "uz": "Ibrohim"
        },
        {
          "w": "يُحِبُّ",
          "r": "خَبَر كَان",
          "rc": "tx",
          "e": "يُحِبُّ كانَning xabari bo'lgan fe'l-jumladir. كانَ fe'l-jumla xabar olganda, bu jumla mahalli nasb holatida deyiladi. Yashirin fo'ili هُوَ — ya'ni Ibrohim — bo'lib, uning Ismoilga muhabbati bu fe'l orqali ifodalanar.",
          "uz": "yaxshi ko'radi"
        },
        {
          "w": "إِسْمَاعِيلَ",
          "r": "مَفعُول بِه",
          "rc": "tb",
          "e": "إِسْمَاعِيلَ يُحِبُّ fe'lining maf'uli bo'lib, nasb holatida kelgan. Gayr munsarif ism sifatida kasra o'rniga fatha qabul qiladi, chunki unda alam va a'jamiylik illatlari bir vaqtda jamlanadi. Muhabbat qaratilgan shaxs — Ismoil — aynan shu maf'ul orqali aniqlanadi.",
          "uz": "Ismoilni"
        },
        {
          "w": "جِدًّا",
          "r": "مَفعُول مُطلَق",
          "rc": "th",
          "e": "جِدًّا daraja va kuchaytirish ma'nosini bildiruvchi zarf bo'lib, يُحِبُّ fe'liga mutaalliq. U muhabbatning darajasini — «juda» — kuchaytiradi va fe'l ma'nosini ta'kidlab, intensivlik qo'shadi. Tanvini fatha bilan nasb holatida zarfiy nasb sifatida kelgan.",
          "uz": "juda"
        }
      ]
    },
    {
      "ar": "وَذَاتَ لَيْلَةٍ رَأَى إِبْرَاهِيمُ فِي الْمَنَامِ أَنَّهُ يَذْبَحُ إِسْمَاعِيلَ.",
      "tr": "Bir kechada Ibrohim tushida Ismoilni so'layotganini ko'rdi.",
      "parts": [
        {
          "w": "وَذَاتَ لَيْلَةٍ",
          "r": "ظَرف زَمَان",
          "rc": "th",
          "e": "وَذَاتَ لَيْلَةٍ vaqt zarfi tarkibi bo'lib, رَأَى fe'liga mutaalliq. ذَاتَ nasb holatida zarfiy nasb alomati bilan kelgan, لَيْلَةٍ esa uning muzofun ilayhi bo'lib, jarr holatida tanvini kasra bilan kelgan. Bu ibtidoiy arab uslubida «muayyan bir kecha» ma'nosini ifodalab, voqea vaqtini belgilaydi.",
          "uz": "bir kechada"
        },
        {
          "w": "رَأَى",
          "r": "فِعل مَاضٍ",
          "rc": "tf",
          "e": "رَأَى o'tgan zamon fe'li bo'lib, bu kontekstda uyquda tush ko'rish ma'nosida qo'llangan. Bu fe'l أَنَّهُ يَذْبَحُ tarkibini saddiy (muayyaliy) maf'ul sifatida boshqaradi. Fo'ili keyingi إِبْرَاهِيمُ bo'lib, uning tushda ko'rgan narsasi rivoyatning burilish nuqtasini tashkil etadi.",
          "uz": "ko'rdi"
        },
        {
          "w": "إِبْرَاهِيمُ",
          "r": "فَاعِل",
          "rc": "tm",
          "e": "إِبْرَاهِيمُ رَأَى fe'lining fo'ili bo'lib, raf' holatida kelgan. Fe'ldan keyin kelgan ochiq ism fo'il vazifasini bajaradi va doimo raf' holatida bo'ladi. Tushni ko'rgan — shu rivoyatning bosh qahramoni Ibrohim ekanini bu so'z tasdiqlaydi.",
          "uz": "Ibrohim"
        },
        {
          "w": "فِي الْمَنَامِ",
          "r": "جَار وَمَجرُور",
          "rc": "th",
          "e": "فِي الْمَنَامِ jar-majrur tarkibi bo'lib, رَأَى fe'liga mutaalliq holda ko'rish qayerda — uyquda, tushda — sodir bo'lganini ifodalaydi. فِي zarfiylik bildiruvchi harf jar, الْمَنَامِ esa ta'rifli ism sifatida jarr holatida kelgan. Bu tarkib ko'rish oddiy ko'rish emas, balki ilohiy tush ekani ta'kidlanishiga xizmat qiladi.",
          "uz": "tushida"
        },
        {
          "w": "أَنَّهُ",
          "r": "حَرف مُشَبَّهة بِالفِعل",
          "rc": "tb",
          "e": "أَنَّهُ أَنَّ va mutakallim zamiri -هُdan tuzilgan tarkib bo'lib, رَأَى fe'lining mazmuniy maf'ulini hosil qiladi. أَنَّ harfi mushabbaha bil-fe'l bo'lib, o'zidan keyin kelgan jumlani ta'kid va muayyanlik ma'nosida nasb holatiga olib kiradi. Ondagi -هُ zamiri Ibrohimga qaytib, keyingi يَذْبَحُ fe'lining ismi sifatida raf' holatida tushuniladi.",
          "uz": "u"
        },
        {
          "w": "يَذْبَحُ",
          "r": "خَبَر أَنَّ",
          "rc": "tx",
          "e": "يَذْبَحُ أَنَّ tarkibining xabari bo'lgan fe'l-jumlasi bo'lib, mahalli nasb holatida. Yashirin fo'ili -هُ zamiri — ya'ni Ibrohim — bo'lib, u so'yish harakatini bajaruvchi sifatida ifodalangan. Bu xabar fe'l-jumlasi tushning aniq mazmunini ochib beradi.",
          "uz": "so'yadi"
        },
        {
          "w": "إِسْمَاعِيلَ",
          "r": "مَفعُول بِه",
          "rc": "tb",
          "e": "إِسْمَاعِيلَ يَذْبَحُ fe'lining maf'uli bo'lib, nasb holatida kelgan. Gayr munsarif ism sifatida fatha nasb alomati sifatida qo'llanilgan. Tushda so'yish harakati qaratilgan shaxs — Ismoil — aynan shu maf'ul orqali belgilanadi.",
          "uz": "Ismoilni"
        }
      ]
    },
    {
      "ar": "وَكَانَ إِبْرَاهِيمُ نَبِيًّا صَادِقًا، وَكَانَ مَنَامُهُ مَنَامًا صَادِقًا.",
      "tr": "Ibrohim rostgo'y payg'ambar edi va uning tushi ham rost edi.",
      "parts": [
        {
          "w": "وَكَانَ",
          "r": "فِعل مَاضٍ نَاقِص",
          "rc": "tf",
          "e": "وَكَانَ birinchi jumlaning noqis o'tgan zamon fe'li bo'lib, ismi إِبْرَاهِيمُni raf', xabari نَبِيًّا صَادِقًani nasb holatida boshqaradi. كانَ o'tmishda bo'lgan doimiy holatni ifodalash uchun qo'llaniladi. Bu fe'l Ibrohimning payg'ambarlik sifatini tarixiy haqiqat sifatida tasdiqlaydi.",
          "uz": "edi"
        },
        {
          "w": "إِبْرَاهِيمُ",
          "r": "اسم كَان",
          "rc": "tm",
          "e": "إِبْرَاهِيمُ birinchi كانَning ismi bo'lib, raf' holatida kelgan. كانَ ismi bo'lgani uchun raf' holatida turadi va keyingi xabar aynan shu shaxs haqida berilganini bildiradi. نَبِيًّا صَادِقًا xabari shu ismga bog'langan.",
          "uz": "Ibrohim"
        },
        {
          "w": "نَبِيًّا صَادِقًا",
          "r": "خَبَر كَان",
          "rc": "tx",
          "e": "نَبِيًّا صَادِقًا birinchi كانَning xabari bo'lib, nasb holatida kelgan. نَبِيًّا asosiy xabar — nasb holatida tanvini fatha bilan — صَادِقًا esa shu xabarni sifatlovchi na't bo'lib, ikkalasi ham xabarning grammatik holatiga muvofiq nasb holatida. Bu tarkib Ibrohimning payg'ambarlik va rostgo'ylik sifatlarini bir vaqtda bayon qiladi.",
          "uz": "rostgo'y payg'ambar"
        },
        {
          "w": "وَكَانَ مَنَامُهُ مَنَامًا صَادِقًا",
          "r": "جُمْلَة اسمِيَّة (كَان)",
          "rc": "tx",
          "e": "وَكَانَ مَنَامُهُ مَنَامًا صَادِقًا ikkinchi كانَ tarkibidan iborat bo'lib, مَنَامُهُ ismi raf', مَنَامًا صَادِقًا esa xabari nasbdir. Ondagi -هُ zamiri Ibrohimga qaytadi. Bu jumla Ibrohimning tushining ilohiy va rost ekanligini payg'ambarlik bilan bog'lab tasdiqlaydi.",
          "uz": "tushi rost tush edi"
        }
      ]
    },
    {
      "ar": "وَكَانَ إِبْرَاهِيمُ خَلِيلَ اللَّهِ، فَأَرَادَ أَنْ يَفْعَلَ مَا أَمَرَهُ اللَّهُ فِي الْمَنَامِ.",
      "tr": "Ibrohim Allohning do'sti edi. Alloh tushda buyurgan narsani qilishni xohladi.",
      "parts": [
        {
          "w": "وَكَانَ",
          "r": "فِعل مَاضٍ نَاقِص",
          "rc": "tf",
          "e": "وَكَانَ noqis o'tgan zamon fe'li bo'lib, ismi إِبْرَاهِيمُni raf', xabari خَلِيلَ اللَّهِni nasb holatida boshqaradi. كانَ Ibrohimning Alloh bilan bo'lgan maxsus munosabatini o'tmishdagi doimiy hol sifatida ifodalaydi. Bu hol keyingi фَأَرَادَ voqeasining sababiga ishora qiladi.",
          "uz": "edi"
        },
        {
          "w": "إِبْرَاهِيمُ",
          "r": "اسم كَان",
          "rc": "tm",
          "e": "إِبْرَاهِيمُ كانَning ismi bo'lib, raf' holatida kelgan. كانَ ismi doimo raf' holatida bo'ladi. خَلِيلَ اللَّهِ xabari aynan shu shaxsga nisbatan berilgan.",
          "uz": "Ibrohim"
        },
        {
          "w": "خَلِيلَ اللَّهِ",
          "r": "خَبَر كَان",
          "rc": "tx",
          "e": "خَلِيلَ اللَّهِ كانَning xabari bo'lib, izofa tarkibida nasb holatida kelgan. خَلِيلَ nasb holatidagi xabar, اللَّهِ esa uning muzofun ilayhi sifatida jarr holatida. Bu izofa tarkibi Ibrohimning Allohga nisbatlangan yaqin do'stlik — xullat — maqomini bayon qiladi.",
          "uz": "Allohning do'sti"
        },
        {
          "w": "فَأَرَادَ",
          "r": "فِعل مَاضٍ",
          "rc": "tf",
          "e": "فَأَرَادَ natija va tafri' ma'nosidagi fe'l bo'lib, faning oldingi holatdan kelib chiqqan natijani bildirishi — ya'ni Allohning do'sti bo'lgani uchun, buyruqni bajarishni istaganini — ko'rsatadi. Yashirin fo'ili Ibrohim bo'lib, iroda fe'li sifatida أَنْ يَفْعَلَ tarkibini boshqaradi. Bu fe'l Ibrohimning imon va itoatining ifodasi.",
          "uz": "va xohladi"
        },
        {
          "w": "أَنْ يَفْعَلَ",
          "r": "مَصدَر مُؤَوَّل (مَفعُول بِه)",
          "rc": "tf",
          "e": "أَنْ يَفْعَلَ أَرَادَ fe'lining maf'uli o'rnida kelgan masdar ta'villi tarkib bo'lib, mahalli nasb holatida. أَنْ harfi muzori' fe'lni mansub holatga olib kiradi va ikkalasi birgalikda masdar ma'nosini beradi. Ibrohim xohlagan amalning o'zini — bajarish niyatini — bildiradi.",
          "uz": "qilishni"
        },
        {
          "w": "مَا أَمَرَهُ اللَّهُ",
          "r": "مَفعُول بِه",
          "rc": "tb",
          "e": "مَا أَمَرَهُ اللَّهُ يَفْعَلَ fe'lining maf'uli bo'lib, مَا ism mavsulidur va «narsa» ma'nosida kelgan. أَمَرَهُ اللَّهُ esa مَاning sila jumlasi bo'lib, -هُ zamiri Ibrohimga qaytadi. Bu tarkib Ibrohimning bajarmoqchi bo'lgan narsasini — Allohning buyrug'ini — aniq ko'rsatadi.",
          "uz": "Alloh buyurgan narsani"
        },
        {
          "w": "فِي الْمَنَامِ",
          "r": "جَار وَمَجرُور",
          "rc": "th",
          "e": "فِي الْمَنَامِ أَمَرَهُ fe'liga bog'langan jar-majrur tarkibi bo'lib, buyruq qaysi holatda — tushda — kelganini bildiradi. فِي zarfiylik bildiruvchi harf jar, الْمَنَامِ esa ta'rifli ism sifatida jarr holatida kelgan. Bu tarkib buyruqning ilohiy tush orqali berilganini ta'kidlaydi.",
          "uz": "tushida"
        }
      ]
    },
    {
      "ar": "وَقَالَ إِبْرَاهِيمُ لِإِسْمَاعِيلَ: ﴿إِنِّي أَرَى فِي الْمَنَامِ أَنِّي أَذْبَحُكَ فَانْظُرْ مَاذَا تَرَى﴾.",
      "tr": "Ibrohim Ismoilga: Men tushimda seni so'layotganimni ko'ryapman. Qanday fikrdasan? — dedi.",
      "parts": [
        {
          "w": "وَقَالَ",
          "r": "فِعل مَاضٍ",
          "rc": "tf",
          "e": "وَقَالَ o'tgan zamon so'zlash fe'li bo'lib, keyingi bevosita nutq iqtibosini boshqaradi. Fo'ili إِبْرَاهِيمُ, muxotabi لِإِسْمَاعِيلَ, nutqning mazmuni esa iqtibos jumlasida kelgan. Arab grammatikasida so'zlash fe'llari to'g'ri nutqni qo'shtirnoqsiz, bevosita kiritadi.",
          "uz": "va dedi"
        },
        {
          "w": "إِبْرَاهِيمُ",
          "r": "فَاعِل",
          "rc": "tm",
          "e": "إِبْرَاهِيمُ وَقَالَ fe'lining fo'ili bo'lib, raf' holatida kelgan. Fe'ldan keyin kelgan ochiq ism fo'il vazifasida bo'lib, doimo raf' holatida turadi. Ismoilga murojaat qilgan shaxsni — Ibrohimni — belgilaydi.",
          "uz": "Ibrohim"
        },
        {
          "w": "لِإِسْمَاعِيلَ",
          "r": "جَار وَمَجرُور",
          "rc": "tmt",
          "e": "لِإِسْمَاعِيلَ jar-majrur tarkibi bo'lib, وَقَالَ fe'liga mutaalliq. لِ harfi jar muxotabiylik — kimga aytilgan — ma'nosini bildiradi, إِسْمَاعِيلَ esa gayr munsarif sifatida kasra o'rniga fatha bilan jarr holatida kelgan. Gap kimga aytilganini aniq ko'rsatadi.",
          "uz": "Ismoilga"
        },
        {
          "w": "إِنِّي",
          "r": "حَرف مُشَبَّهة بِالفِعل",
          "rc": "tb",
          "e": "إِنِّي إِنَّ harfi va mutakallim zamiri -يdan tuzilgan bo'lib, xabar jumlasini ta'kidlaydi. إِنَّ harfi mushabbaha bil-fe'l bo'lib, o'zidan keyingi ismni nasb holatiga olib kiradi. Mutakallim zamiri -ي ismi o'rnida turadi va keyingi fe'l-jumla xabari sifatida keladi.",
          "uz": "albatta men"
        },
        {
          "w": "أَرَى",
          "r": "خَبَر إِنَّ",
          "rc": "tx",
          "e": "أَرَى إِنَّ tarkibining xabari bo'lgan fe'l-jumlasi bo'lib, mahalli nasb holatida. Yashirin fo'ili أَنَا — ya'ni Ibrohim — bo'lib, uning ko'rayotganini bildiradi. Fe'lning muzore' shaklida kelishi harakatning hozirgi paytda davom etayotganini ko'rsatadi.",
          "uz": "ko'ryapman"
        },
        {
          "w": "فِي الْمَنَامِ",
          "r": "جَار وَمَجرُور",
          "rc": "th",
          "e": "فِي الْمَنَامِ أَرَى fe'liga bog'langan jar-majrur tarkibi bo'lib, ko'rish qayerda — tushda — sodir bo'layotganini bildiradi. فِي zarfiylik bildiruvchi harf jar, الْمَنَامِ esa jarr holatida ta'rifli ism. Bu tarkib ko'rishning oddiy emas, balki ilohiy tush ekanini ta'kidlaydi.",
          "uz": "tushida"
        },
        {
          "w": "أَنِّي أَذْبَحُكَ",
          "r": "مَصدَر مُؤَوَّل (مَفعُول بِه)",
          "rc": "tb",
          "e": "أَنِّي أَذْبَحُكَ أَرَى fe'lining maf'uli o'rnida kelgan masdar ta'villi tarkib bo'lib, tushda ko'rilgan narsaning mazmunini beradi. أَنِّي إِنِّي kabi tuzilgan bo'lib, أَذْبَحُكَ uning xabari. Ondagi -كَ zamiri Ismoilga qaytib, so'yish harakati kim tomonga qaratilganini ko'rsatadi.",
          "uz": "seni so'yayotganimni"
        },
        {
          "w": "فَانْظُرْ",
          "r": "فِعل أَمر",
          "rc": "tf",
          "e": "فَانْظُرْ buyruq fe'li bo'lib, fao natija ma'nosida oldingi xabardan keyingi amalga o'tishni bildiradi. Muhotab — muxotab siyg'asida — Ismoilga qaratilgan bu buyruq uning o'z fikrini bildirishi talab qilinayotganini ko'rsatadi. Ibrohimning bolasini hurmat qilishi va uning fikriga e'tibor berishi bu amr orqali namoyon bo'ladi.",
          "uz": "qara"
        },
        {
          "w": "مَاذَا",
          "r": "اسم اسْتِفهَام",
          "rc": "tb",
          "e": "مَاذَا مَا va ذَا so'roq olmoshidan tuzilgan murakkab so'roq bo'lib, تَرَى fe'lining mazmuniy maf'uli sifatida «nima» yoki «qaysi fikr» ma'nosida ishlatilgan. Arab grammatikasida مَاذَا birgalikda bir so'roq olmoshi sifatida qabul qilinadi. Bu so'roq Ismoildan ko'rish — fikrlash — harakatining natijasini so'raydi.",
          "uz": "nimadan"
        },
        {
          "w": "تَرَى",
          "r": "فِعل مُضَارِع",
          "rc": "tf",
          "e": "تَرَى muhotab siyg'asidagi muzore' fe'l bo'lib, Ismoilga qaratilgan. Yashirin fo'ili أَنْتَ — ya'ni Ismoil — bo'lib, uning qarashi va fikri so'ralmoqda. مَاذَا so'roq olmoshi bilan birgalikda «nima deb o'ylaysan» yoki «fikring nima» ma'nosini hosil qiladi.",
          "uz": "ko'rasan"
        }
      ]
    },
    {
      "ar": "﴿قَالَ يَا أَبَتِ افْعَلْ مَا تُؤْمَرُ سَتَجِدُنِي إِنْ شَاءَ اللَّهُ مِنَ الصَّابِرِينَ﴾.",
      "tr": "U (Ismoil) dedi: Otajon, senga buyurilgan narsani qil. Alloh xohlasa, meni sabr qiluvchilardan topasan.",
      "parts": [
        {
          "w": "قَالَ",
          "r": "فِعل مَاضٍ",
          "rc": "tf",
          "e": "قَالَ o'tgan zamon javob fe'li bo'lib, yashirin fo'ili Ismoil. Oldingi Ibrohimning savoliga javoban aytilgan nutqni kiritadi. Arab rivoyat uslubida قَالَ so'zlash fe'li bevosita nutqni hech qanday qo'shimcha belgisiz kiritadi.",
          "uz": "dedi"
        },
        {
          "w": "يَا أَبَتِ",
          "r": "أُسلُوب نِدَاء",
          "rc": "tb",
          "e": "يَا أَبَتِ nido tarkibi bo'lib, يَا nido harfi, أَبَتِ esa munadoga — chaqirilayotgan shaxsga — ishora qiladi. أَبَ so'ziga قصر ta'biri bilan -تِ qo'shilishi muannaslik emas, balki mehribonlik va ixtisor ma'nosini bildiradi. Ismoil otasi Ibrohimga chuqur hurmat va muhabbat bilan murojaat qilmoqda.",
          "uz": "otajon"
        },
        {
          "w": "افْعَلْ",
          "r": "فِعل أَمر",
          "rc": "tf",
          "e": "افْعَلْ buyruq fe'li bo'lib, muhotab Ibrohimga qaratilgan. Ismoil otasiga buyruq emas, balki ruxsat va ijozat ma'nosida — «qilaver» — aytmoqda. Bu fe'l Ismoilning to'liq itoat va sabr bilan Allohning amriga rozi bo'lganini ifodalaydi.",
          "uz": "qil"
        },
        {
          "w": "مَا تُؤْمَرُ",
          "r": "مَفعُول بِه",
          "rc": "tb",
          "e": "مَا تُؤْمَرُ افْعَلْ fe'lining maf'uli bo'lib, مَا ism mavsuli «narsa» ma'nosida. تُؤْمَرُ esa uning sila jumlasi bo'lib, majhul siyg'ada kelgan — ya'ni buyruq beruvchi aytilmagan, Alloh nazarda tutilgan. Bu tarkib Ibrohimga buyurilgan narsaning o'zini — so'yish amrini — bildiradi.",
          "uz": "senga buyurilgan narsani"
        },
        {
          "w": "سَتَجِدُنِي",
          "r": "فِعل مُضَارِع",
          "rc": "tf",
          "e": "سَتَجِدُنِي sin ta'kid harfi bilan kelasi zamonni bildiruvchi muzore' fe'l bo'lib, muhotab Ibrohimga qaratilgan. Yashirin fo'ili أَنْتَ — Ibrohim, -نِي zamiri esa birinchi shaxs — Ismoil. Bu fe'l ikki maf'ul oluvchi (va'daniy) fe'l bo'lib, birinchi maf'ul -نِي, ikkinchisi مِنَ الصَّابِرِينَdir.",
          "uz": "meni topasan"
        },
        {
          "w": "إِنْ شَاءَ اللَّهُ",
          "r": "جُمْلَة شَرطِيَّة",
          "rc": "th",
          "e": "إِنْ شَاءَ اللَّهُ shart jumlasi bo'lib, إِنْ shart harfi, شَاءَ shart fe'li, اللَّهُ esa uning fo'ilidir. Javob jumlasi — جزاء — yashirin bo'lib, oldingi سَتَجِدُنِي fe'li uni anglatadi. Bu iborani ishlatish Ismoilning o'z irodasini Allohning xohishiga bog'lashi — tawakkul — hissini ifodalaydi.",
          "uz": "Alloh xohlasa"
        },
        {
          "w": "مِنَ الصَّابِرِينَ",
          "r": "مَفعُول بِه ثَانٍ",
          "rc": "tmt",
          "e": "مِنَ الصَّابِرِينَ سَتَجِدُنِي fe'lining ikkinchi maf'uli sifatida jar-majrur tarkibida kelgan. مِنَ toifa bildiruvchi harf jar, الصَّابِرِينَ esa jamlovchi ism sifatida jarr holatida. Bu tarkib Ismoilning qaysi toifadan — sabr qiluvchilardan — topilishini ko'rsatib, uning yuksak ma'naviy holatini bayon qiladi.",
          "uz": "sabr qiluvchilardan"
        }
      ]
    },
    {
      "ar": "وَأَخَذَ إِبْرَاهِيمُ إِسْمَاعِيلَ مَعَهُ وَأَخَذَ سِكِّينًا.",
      "tr": "Ibrohim Ismoilni o'zi bilan oldi va pichoq oldi.",
      "parts": [
        {
          "w": "وَأَخَذَ",
          "r": "فِعل مَاضٍ",
          "rc": "tf",
          "e": "وَأَخَذَ o'tgan zamon fe'li bo'lib, Ibrohimning Ismoilni o'zi bilan olib ketish harakatini bildiradi. Fo'ili keyingi إِبْرَاهِيمُ bo'lib, birinchi أَخَذَ Ismoilni maf'ul sifatida boshqaradi. Bu fe'l rivoyatdagi qurbonlik safarining boshlanishini ifodalaydi.",
          "uz": "oldi"
        },
        {
          "w": "إِبْرَاهِيمُ",
          "r": "فَاعِل",
          "rc": "tm",
          "e": "إِبْرَاهِيمُ وَأَخَذَ fe'lining fo'ili bo'lib, raf' holatida kelgan. Fe'ldan keyin kelgan ochiq ism fo'il vazifasini bajaradi va doimo raf' holatida bo'ladi. Olib ketish harakatini bajargan shaxsni — Ibrohimni — ko'rsatadi.",
          "uz": "Ibrohim"
        },
        {
          "w": "إِسْمَاعِيلَ",
          "r": "مَفعُول بِه",
          "rc": "tb",
          "e": "إِسْمَاعِيلَ birinchi وَأَخَذَ fe'lining maf'uli bo'lib, nasb holatida kelgan. Gayr munsarif ism sifatida kasra o'rniga fatha bilan kelgan. Ibrohim o'zi bilan olib ketgan shaxsni — Ismoilni — belgilaydi.",
          "uz": "Ismoilni"
        },
        {
          "w": "مَعَهُ",
          "r": "ظَرف مَكَان",
          "rc": "th",
          "e": "مَعَهُ ma'iyyat zarfi bo'lib, birinchi وَأَخَذَ fe'liga mutaalliq. مَعَ birga bo'lish va hamrohlik ma'nosidagi zarf, -هُ zamiri esa Ibrohimga qaytadi. Bu zarf Ismoilning yakka holda emas, balki otasi bilan olib ketilganini ko'rsatadi.",
          "uz": "o'zi bilan"
        },
        {
          "w": "وَأَخَذَ",
          "r": "فِعل مَاضٍ",
          "rc": "tf",
          "e": "Ikkinchi وَأَخَذَ oldingi fe'lga vov atf bilan bog'langan mustaqil fe'l bo'lib, yashirin fo'ili Ibrohim. Bu safar alingan narsa Ismoil emas, balki سِكِّينًا — pichoq. Arab rivoyat uslubida harakatlarning ketma-ketligi fe'llarning atf bilan birikishi orqali ifodalanadi.",
          "uz": "oldi"
        },
        {
          "w": "سِكِّينًا",
          "r": "مَفعُول بِه",
          "rc": "tb",
          "e": "سِكِّينًا ikkinchi وَأَخَذَ fe'lining maf'uli bo'lib, nasb holatida tanvini fatha bilan kelgan. Noaniqlik — tanvin — pichoqning ma'lum bir pichoq emasligini, balki qandaydir pichoq ekanligini anglatadi. Ibrohim olgan asbobni — qurbonlik uchun zarur pichoqni — bildiradi.",
          "uz": "pichoq"
        }
      ]
    },
    {
      "ar": "وَلَمَّا بَلَغَ إِبْرَاهِيمُ مِنًى، أَرَادَ أَنْ يَذْبَحَ إِسْمَاعِيلَ.",
      "tr": "Ibrohim Minoga yetganda, Ismoilni so'yishni xohladi.",
      "parts": [
        {
          "w": "وَلَمَّا",
          "r": "ظَرف زَمَان",
          "rc": "th",
          "e": "وَلَمَّا vaqt zarfi bo'lib, ikki voqeani — yetib borish va iroda qilishni — shartli-vaqtiy aloqa bilan bog'laydi. لَمَّا «qachonki» ma'nosidagi adat ado bo'lib, fe'l-jumla shart, keyingi جواب esa natija. Bu aloqa Minoga yetib borish bilan so'yish niyatining bir vaqtda bo'lganini ko'rsatadi.",
          "uz": "qachonki"
        },
        {
          "w": "بَلَغَ",
          "r": "فِعل مَاضٍ",
          "rc": "tf",
          "e": "بَلَغَ «yetib borish» ma'nosidagi o'tgan zamon fe'li bo'lib, لَمَّاning shart fe'lidir. Fo'ili إِبْرَاهِيمُ, manzili مِنًى bo'lib, nasb holatida maf'ul vazifasida kelgan. Bu fe'l qurbonlik safarida muhim bosqich — muayyan joyga yetib borish — ni bildiradi.",
          "uz": "yetdi"
        },
        {
          "w": "إِبْرَاهِيمُ",
          "r": "فَاعِل",
          "rc": "tm",
          "e": "إِبْرَاهِيمُ بَلَغَ fe'lining fo'ili bo'lib, raf' holatida kelgan. Fe'ldan keyin kelgan ochiq ism fo'il sifatida doimo raf' holatida turadi. Minoga yetib borgan shaxs — Ibrohim — aynan shu fo'il orqali belgilanadi.",
          "uz": "Ibrohim"
        },
        {
          "w": "مِنًى",
          "r": "مَفعُول بِه",
          "rc": "tb",
          "e": "مِنًى بَلَغَ fe'lining manzil maf'uli bo'lib, nasb holatida kelgan. Arab grammatikasida بَلَغَ fe'li介词siz to'g'ridan-to'g'ri manzilni nasb holatida olishi mumkin. مِنًى gayr munsarif joy ism sifatida tanvinsiz fatha bilan kelgan.",
          "uz": "Minoga"
        },
        {
          "w": "أَرَادَ",
          "r": "فِعل مَاضٍ",
          "rc": "tf",
          "e": "أَرَادَ لَمَّaning javob fe'li bo'lib, yashirin fo'ili Ibrohim. Bu fe'l Minoga yetib borganidan keyin sodir bo'lgan — Ismoilni so'yishni niyat qilish — harakatni bildiradi. أَرَادَ iroda fe'li sifatida أَنْ يَذْبَحَ tarkibini boshqaradi.",
          "uz": "xohladi"
        },
        {
          "w": "أَنْ يَذْبَحَ",
          "r": "مَصدَر مُؤَوَّل (مَفعُول بِه)",
          "rc": "tf",
          "e": "أَنْ يَذْبَحَ أَرَادَ fe'lining maf'uli o'rnida kelgan masdar ta'villi tarkib bo'lib, mahalli nasb holatida. أَنْ harfi muzori' fe'lni mansub holatga olib kiradi, ikkalasi birgalikda «so'yish» masdarini anglatadi. Ibrohimning niyat qilingan amalini — Ismoilni so'yishni — bildiradi.",
          "uz": "so'yishni"
        },
        {
          "w": "إِسْمَاعِيلَ",
          "r": "مَفعُول بِه",
          "rc": "tb",
          "e": "إِسْمَاعِيلَ يَذْبَحَ fe'lining maf'uli bo'lib, nasb holatida gayr munsarif sifatida fatha bilan kelgan. Niyat qilingan so'yish harakati qaratilgan shaxs — Ismoil — shu maf'ul orqali belgilanadi. Bu so'z rivoyatning eng ta'sirchan lahzasini — ota va o'g'il sinavini — xotiralaydi.",
          "uz": "Ismoilni"
        }
      ]
    },
    {
      "ar": "وَاضْطَجَعَ إِسْمَاعِيلُ عَلَى الْأَرْضِ.",
      "tr": "Ismoil yerga yonboshladi.",
      "parts": [
        {
          "w": "وَاضْطَجَعَ",
          "r": "فِعل مَاضٍ",
          "rc": "tf",
          "e": "وَاضْطَجَعَ «yonboshladi, yotdi» ma'nosidagi o'tgan zamon fe'li bo'lib, اِفْتَعَلَ vaznidagi mutor'i' fe'ldir. Fo'ili keyingi إِسْمَاعِيلُ bo'lib, Ismoilning itoat bilan yerga yotish harakatini bildiradi. Bu harakat Ismoilning so'yilishga rozi ekanini va Ibrohimning ishini osonlashtirganini ko'rsatadi.",
          "uz": "yonboshladi"
        },
        {
          "w": "إِسْمَاعِيلُ",
          "r": "فَاعِل",
          "rc": "tm",
          "e": "إِسْمَاعِيلُ وَاضْطَجَعَ fe'lining fo'ili bo'lib, raf' holatida kelgan. Fe'ldan keyin kelgan ochiq ism fo'il sifatida raf' holatida turadi. Yonboshlash harakatini bajargan shaxsni ko'rsatadi.",
          "uz": "Ismoil"
        },
        {
          "w": "عَلَى الْأَرْضِ",
          "r": "جَار وَمَجرُور",
          "rc": "tmt",
          "e": "عَلَى الْأَرْضِ jar-majrur tarkibi bo'lib, وَاضْطَجَعَ fe'liga mutaalliq. عَلَى ustida bo'lish ma'nosidagi harf jar, الْأَرْضِ esa ta'rifli ism sifatida jarr holatida kelgan. Bu tarkib Ismoil qayerga — yerga — yonboshlaganini ko'rsatib, so'yilishga tayyor bo'lganini ifodalaydi.",
          "uz": "yerga"
        }
      ]
    },
    {
      "ar": "وَأَرَادَ إِبْرَاهِيمُ أَنْ يَذْبَحَهُ فَوَضَعَ السِّكِينَ عَلَى حُلْقُومِ إِسْمَاعِيلَ.",
      "tr": "Ibrohim uni so'ymoqchi bo'ldi va pichoqni Ismoilning halqumiga qo'ydi.",
      "parts": [
        {
          "w": "وَأَرَادَ",
          "r": "فِعل مَاضٍ",
          "rc": "tf",
          "e": "وَأَرَادَ Ibrohimning niyatini bildiruvchi iroda fe'li bo'lib, xohlangan amal أَنْ يَذْبَحَهُ bilan ifodalangan. Fo'ili إِبْرَاهِيمُ, bu fe'l rivoyatning kulminatsiya lahzasida — Ibrohim so'ymoqchi bo'lgan paytda — turadi. Oldingi وَاضْطَجَعَ harakatiga ketma-ket bog'langan.",
          "uz": "xohladi"
        },
        {
          "w": "إِبْرَاهِيمُ",
          "r": "فَاعِل",
          "rc": "tm",
          "e": "إِبْرَاهِيمُ وَأَرَادَ fe'lining fo'ili bo'lib, raf' holatida kelgan. Niyat qilgan shaxsni — Ibrohimni — belgilaydi va keyingi فَوَضَعَ harakatining ham yashirin fo'ili sifatida tushuniladi.",
          "uz": "Ibrohim"
        },
        {
          "w": "أَنْ يَذْبَحَهُ",
          "r": "مَصدَر مُؤَوَّل (مَفعُول بِه)",
          "rc": "tf",
          "e": "أَنْ يَذْبَحَهُ أَرَادَ fe'lining maf'uli o'rnida kelgan masdar ta'villi tarkib bo'lib, mahalli nasb holatida. أَنْ muzori' fe'lni mansub holatga olib kiradi, -هُ zamiri esa Ismoilga qaytib, so'yish harakati kimga qaratilganini ko'rsatadi. Bu tarkib Ibrohimning niyatini aniq ifodalaydi.",
          "uz": "uni so'yishni"
        },
        {
          "w": "فَوَضَعَ",
          "r": "فِعل مَاضٍ",
          "rc": "tf",
          "e": "فَوَضَعَ fao-natija bog'lovchi bilan kelgan o'tgan zamon fe'li bo'lib, iroda qilishning darhol natijasi sifatida pichoqni qo'yish harakatini bildiradi. Yashirin fo'ili Ibrohim bo'lib, bu harakatning tezkor sodir bo'lganini فَ bog'lovchi ta'kidlaydi.",
          "uz": "qo'ydi"
        },
        {
          "w": "السِّكِينَ",
          "r": "مَفعُول بِه",
          "rc": "tb",
          "e": "السِّكِينَ فَوَضَعَ fe'lining maf'uli bo'lib, nasb holatida kelgan. Ta'rif harfi الـ bilan kelishi oldin zikr qilingan muayyan pichoqga — Ibrohim olib chiqqan pichoqqa — ishora qiladi. Qo'yilgan narsa shu aniq pichoq ekanini ko'rsatadi.",
          "uz": "pichoqni"
        },
        {
          "w": "عَلَى حُلْقُومِ إِسْمَاعِيلَ",
          "r": "جَار وَمَجرُور",
          "rc": "tmt",
          "e": "عَلَى حُلْقُومِ إِسْمَاعِيلَ فَوَضَعَ fe'liga bog'langan jar-majrur tarkibi bo'lib, pichoq qo'yilgan joyni aniq ko'rsatadi. عَلَى ustida bo'lish ma'nosidagi harf jar, حُلْقُومِ esa jarr holatida muzof, إِسْمَاعِيلَ esa gayr munsarif muzofun ilayhi. Bu tarkib rivoyatning eng ta'sirchan va dramatik lahzasini ifodalaydi.",
          "uz": "Ismoilning halqumiga"
        }
      ]
    },
    {
      "ar": "وَلَكِنَّ اللَّهَ يُحِبُّ أَنْ يَرَى هَلْ يَفْعَلُ خَلِيلُهُ مَا يَأْمُرُهُ وَهَلْ يُحِبُّ اللَّهَ أَكْثَرَ أَوْ يُحِبُّ ابْنَهُ أَكْثَرَ.",
      "tr": "Lekin Alloh o'z do'sti (Ibrohim) buyurgan narsani qiladimi va Allohni ko'proq sevadimi yoki o'g'lini — buni ko'rishni xohladi.",
      "parts": [
        {
          "w": "وَلَكِنَّ",
          "r": "حَرف اسْتِدرَاك",
          "rc": "tb",
          "e": "وَلَكِنَّ oldingi dramatik vaziyatga qarama-qarshi ma'noni kirituvchi istidrok harfi bo'lib, oldingi jumlaga zid yoki qo'shimcha nuqta nazarni bildiradi. لَكِنَّ harfi mushabbaha bil-fe'l turkumiga kirib, o'zidan keyingi ismni nasb holatiga olib kiradi. Bu so'z vaziyatning ilohiy maqsad va hikmatini ochib berishga kirish vazifasini bajaradi.",
          "uz": "lekin"
        },
        {
          "w": "اللَّهَ",
          "r": "اسم لَكِنَّ",
          "rc": "tm",
          "e": "اللَّهَ لَكِنَّning ismi bo'lib, nasb holatida kelgan. لَكِنَّ harfi mushabbaha bil-fe'l turkumi sifatida ismini nasb holatida boshqaradi. Keyingi يُحِبُّ fe'l-jumlasi aynan shu zot haqidagi xabarni beradi.",
          "uz": "Alloh"
        },
        {
          "w": "يُحِبُّ",
          "r": "خَبَر لَكِنَّ",
          "rc": "tx",
          "e": "يُحِبُّ لَكِنَّning xabari bo'lgan fe'l-jumlasi bo'lib, mahalli nasb holatida. Yashirin fo'ili هُوَ — Alloh — bo'lib, Uning ko'rishni istashini bildiradi. Alloh bu sinov orqali imon va muhabbatni amalda ko'rmoqchi bo'lgan ilohiy hikmatini ifodalaydi.",
          "uz": "yaxshi ko'radi"
        },
        {
          "w": "أَنْ يَرَى",
          "r": "مَصدَر مُؤَوَّل (مَفعُول بِه)",
          "rc": "tf",
          "e": "أَنْ يَرَى يُحِبُّ fe'lining maf'uli o'rnida kelgan masdar ta'villi tarkib bo'lib, mahalli nasb holatida. أَنْ muzori' fe'lni mansub holatga olib kiradi. Allohning ko'rishni — yani sinov natijasini kuzatishni — istashini bildiradi.",
          "uz": "ko'rishni"
        },
        {
          "w": "هَلْ يَفْعَلُ خَلِيلُهُ مَا يَأْمُرُهُ",
          "r": "جُمْلَة اسْتِفهَامِيَّة",
          "rc": "th",
          "e": "هَلْ يَفْعَلُ خَلِيلُهُ مَا يَأْمُرُهُ أَنْ يَرَى fe'lining mazmunini — ko'rilishi istalgan narsani — tashkil etuvchi so'roq-hol jumlasi. هَلْ tasdiq yo inkor so'roq harfi, خَلِيلُهُ يَفْعَلُning fo'ili, -هُ zamiri Allohga qaytib, Ibrohimni anglatadi. مَا يَأْمُرُهُ esa يَفْعَلُning maf'uli.",
          "uz": "do'sti buyurgan narsani qiladimi"
        },
        {
          "w": "وَهَلْ يُحِبُّ اللَّهَ أَكْثَرَ",
          "r": "جُمْلَة اسْتِفهَامِيَّة مَعطُوفَة",
          "rc": "th",
          "e": "وَهَلْ يُحِبُّ اللَّهَ أَكْثَرَ oldingi so'roqqa vov atf bilan bog'langan ikkinchi so'roq jumlasi. اللَّهَ يُحِبُّning maf'uli nasb holatida, أَكْثَرَ esa daraja — afzallik — bildiruvchi zarf. Bu so'roq sinovning ikkinchi jihatini — Allohga bo'lgan muhabbatning darajasini — ochib beradi.",
          "uz": "Allohni ko'proq sevadimi"
        },
        {
          "w": "أَوْ يُحِبُّ ابْنَهُ أَكْثَرَ",
          "r": "جُمْلَة اسْتِفهَامِيَّة مَعطُوفَة",
          "rc": "th",
          "e": "أَوْ يُحِبُّ ابْنَهُ أَكْثَرَ أَوْ tanlov bog'lovchisi bilan kelgan uchinchi so'roq jumlasi. ابْنَهُ izofa tarkibida nasb holatida maf'ul bo'lib, -هُ zamiri Ibrohimga qaytadi. Bu so'roq ilohiy sinovning mohiyatini — Allohga muhabbat yoki o'g'ilga muhabbat — aks ettiradi.",
          "uz": "yoki o'g'lini ko'proq sevadimi"
        }
      ]
    },
    {
      "ar": "وَنَجَحَ إِبْرَاهِيمُ فِي الِامْتِحَانِ.",
      "tr": "Ibrohim imtihonda muvaffaqiyat qozondi.",
      "parts": [
        {
          "w": "وَنَجَحَ",
          "r": "فِعل مَاضٍ",
          "rc": "tf",
          "e": "وَنَجَحَ «muvaffaqiyatga erishdi, o'tdi» ma'nosidagi o'tgan zamon fe'li bo'lib, sinovning ijobiy natijasini bildiradi. Vov atf bilan oldingi voqealarga bog'langan bu fe'l rivoyatdagi dramatik to'liq imtihonning xulosasini beradi. Fo'ili keyingi إِبْرَاهِيمُ bo'lib, gapning asosiy xabarini tashkil etadi.",
          "uz": "muvaffaqiyat qozondi"
        },
        {
          "w": "إِبْرَاهِيمُ",
          "r": "فَاعِل",
          "rc": "tm",
          "e": "إِبْرَاهِيمُ وَنَجَحَ fe'lining fo'ili bo'lib, raf' holatida kelgan. Fe'ldan keyin kelgan ochiq ism fo'il sifatida doimo raf' holatida turadi. Sinovda muvaffaq bo'lgan shaxs — Ibrohim — aynan shu fo'il orqali belgilanadi.",
          "uz": "Ibrohim"
        },
        {
          "w": "فِي الِامْتِحَانِ",
          "r": "جَار وَمَجرُور",
          "rc": "tmt",
          "e": "فِي الِامْتِحَانِ jar-majrur tarkibi bo'lib, وَنَجَحَ fe'liga mutaalliq. فِي zarfiylik bildiruvchi harf jar, الِامْتِحَانِ esa ta'rifli ism sifatida jarr holatida kelgan. Bu tarkib muvaffaqiyat qaysi sohada — ilohiy sinovda — erishilganini aniq ko'rsatadi.",
          "uz": "imtihonda"
        }
      ]
    },
    {
      "ar": "فَأَرْسَلَ اللَّهُ جِبْرِيلَ بِكَبْشٍ مِنَ الْجَنَّةِ وَقَالَ: اذْبَحْ هَذَا وَلَا تَذْبَحْ إِسْمَاعِيلَ.",
      "tr": "Alloh Jibroilni jannatdan bir qo'chqor bilan yubordi va: Buni so'y, Ismoilni so'yma — dedi.",
      "parts": [
        {
          "w": "فَأَرْسَلَ",
          "r": "فِعل مَاضٍ",
          "rc": "tf",
          "e": "فَأَرْسَلَ fao-natija bog'lovchi bilan kelgan o'tgan zamon fe'li bo'lib, sinovdan o'tishning darhol ilohiy natijasini bildiradi. فَ Ibrohimning muvaffaqiyatidan keyingi ilohiy javobni ta'kidlaydi. Fo'ili اللَّهُ bo'lib, yuborish amalining sohibi Alloh ekanini ko'rsatadi.",
          "uz": "yubordi"
        },
        {
          "w": "اللَّهُ",
          "r": "فَاعِل",
          "rc": "tm",
          "e": "اللَّهُ فَأَرْسَلَ fe'lining fo'ili bo'lib, raf' holatida kelgan. Fe'ldan keyin kelgan ochiq ism fo'il sifatida doimo raf' holatida turadi. Yuborish amalining egasi — Alloh — shu fo'il orqali aniq belgilanadi.",
          "uz": "Alloh"
        },
        {
          "w": "جِبْرِيلَ",
          "r": "مَفعُول بِه",
          "rc": "tb",
          "e": "جِبْرِيلَ فَأَرْسَلَ fe'lining maf'uli bo'lib, nasb holatida kelgan. Gayr munsarif ism sifatida fatha nasb alomati sifatida qo'llanilgan. Alloh tomonidan yuborilgan ilohiy elchi — Jibroil — shu maf'ul orqali belgilanadi.",
          "uz": "Jibroilni"
        },
        {
          "w": "بِكَبْشٍ",
          "r": "جَار وَمَجرُور",
          "rc": "tmt",
          "e": "بِكَبْشٍ jar-majrur tarkibi bo'lib, فَأَرْسَلَ fe'liga mutaalliq. بِ «bilan» ma'nosidagi mulozamat bildiruvchi harf jar, كَبْشٍ esa noaniq ism sifatida tanvini kasra bilan jarr holatida kelgan. Jibril nima bilan — qo'chqor bilan — yuborilganini ko'rsatadi.",
          "uz": "qo'chqor bilan"
        },
        {
          "w": "مِنَ الْجَنَّةِ",
          "r": "جَار وَمَجرُور",
          "rc": "tmt",
          "e": "مِنَ الْجَنَّةِ كَبْشٍ ni aniqlovchi jar-majrur tarkibi bo'lib, قo'chqorning qayerdan kelganini — kelib chiqish manbasini — bildiradi. مِنَ ibtido ma'nosidagi harf jar, الْجَنَّةِ esa ta'rifli ism sifatida jarr holatida. Bu tarkib qo'chqorning oddiy emas, ilohiy manbadan — jannatdan — kelganini ta'kidlaydi.",
          "uz": "jannatdan"
        },
        {
          "w": "وَقَالَ",
          "r": "فِعل مَاضٍ",
          "rc": "tf",
          "e": "وَقَالَ oldingi yuborishga vov atf bilan bog'langan so'zlash fe'li bo'lib, yashirin fo'ili Alloh. Keyingi buyruqlar bevosita ilohiy nutq sifatida kiritilmoqda. Arab grammatikasida قَالَ fe'li to'g'ri nutqni bevosita kiritish uchun qo'llaniladi.",
          "uz": "va dedi"
        },
        {
          "w": "اذْبَحْ",
          "r": "فِعل أَمر",
          "rc": "tf",
          "e": "اذْبَحْ buyruq fe'li bo'lib, muhotab Ibrohimga qaratilgan ilohiy amr. Bu buyruq Ibrohimga so'yilishi kerak bo'lgan narsa — qo'chqor — ekanini bildirib, Ismoilni so'ymaslik amrini ham bervosita tayyorlaydi. Amrning qisqa va aniq kelishi ilohiy buyruqning qat'iy xususiyatini ko'rsatadi.",
          "uz": "so'y"
        },
        {
          "w": "هَذَا",
          "r": "مَفعُول بِه",
          "rc": "tb",
          "e": "هَذَا اذْبَحْ fe'lining maf'uli bo'lib, nasb holatida kelgan ism ishorasi. هَذَا yaqin masofadagi narsaga ishora qiluvchi mufradi muannaslik ko'rsatib, Jibroil olib kelgan jannat qo'chqoriga ishora qiladi. So'yilishi buyurilgan narsa — qo'chqor — shu olmosh orqali aniqlanadi.",
          "uz": "bu"
        },
        {
          "w": "وَلَا تَذْبَحْ",
          "r": "فِعل نَهي",
          "rc": "tf",
          "e": "وَلَا تَذْبَحْ nahy — man qilish — shaklidagi fe'l bo'lib, لَا nafy-nahy harfi, تَذْبَحْ esa jazmli muzore' fe'lidir. Muhotab Ibrohimga Ismoilni so'ymaslikni buyuradi. Bu nahy oldingi amr bilan zidlikda rivoyatning oxirida — ilohiy rahmat va sinavning xulosasini — bildiradi.",
          "uz": "va so'yma"
        },
        {
          "w": "إِسْمَاعِيلَ",
          "r": "مَفعُول بِه",
          "rc": "tb",
          "e": "إِسْمَاعِيلَ وَلَا تَذْبَحْ fe'lining maf'uli bo'lib, nasb holatida gayr munsarif sifatida fatha bilan kelgan. Man qilingan so'yish harakati qaratilmasligi kerak bo'lgan shaxs — Ismoil — shu maf'ul orqali belgilanadi. Bu so'z bilan ilohiy rahmat va sinovning asosiy natijasi yakunlanadi.",
          "uz": "Ismoilni"
        }
      ]
    },
    {
      "ar": "صَلَّى اللَّهُ عَلَى إِبْرَاهِيمَ الْخَلِيلِ وَسَلَّمَ.",
      "tr": "Allohning salavoti va salomi Ibrohim — Xalil (do'st)ga bo'lsin.",
      "parts": [
        {
          "w": "صَلَّى اللَّهُ",
          "r": "فِعل وَفَاعِل",
          "rc": "tf",
          "e": "صَلَّى اللَّهُ duo va salavot fe'li bilan fo'il tarkibi bo'lib, صَلَّى «salavot yubordi» ma'nosida, اللَّهُ esa uning fo'ili raf' holatida. Bu iborani ishlatish arab islomiy adabiyotida payg'ambarlarga duo qilishning an'anaviy shaklidir. Salavotning egasi Alloh, mo'ljallanuvchisi esa keyingi عَلَى tarkibida keladi.",
          "uz": "Allohning salovoti"
        },
        {
          "w": "عَلَى إِبْرَاهِيمَ",
          "r": "جَار وَمَجرُور",
          "rc": "tmt",
          "e": "عَلَى إِبْرَاهِيمَ jar-majrur tarkibi bo'lib, صَلَّى fe'liga mutaalliq. عَلَى yo'nalish va nisbat bildiruvchi harf jar, إِبْرَاهِيمَ esa gayr munsarif sifatida fatha bilan jarr holatida kelgan. Salavot kimga qaratilganini — Ibrohimga — aniq ko'rsatadi.",
          "uz": "Ibrohimga"
        },
        {
          "w": "الْخَلِيلِ",
          "r": "نَعت (صِفَة)",
          "rc": "ts",
          "e": "الْخَلِيلِ إِبْرَاهِيمَning na'ti — sifati yoki laqabi bo'lib, oldingi ismga grammatik muvofiqlikda jarr holatida kelgan. Na't qoidasiga ko'ra u o'rnini bosayotgan ism bilan son, jins, ta'rif va holatda mos bo'ladi. Bu laqab Ibrohimning Alloh bilan bo'lgan maxsus do'stlik — xullat — maqomini ta'kidlaydi.",
          "uz": "do'st (Xalil)"
        },
        {
          "w": "وَسَلَّمَ",
          "r": "فِعل مَعطُوف",
          "rc": "tf",
          "e": "وَسَلَّمَ صَلَّىga vov atf bilan bog'langan duo fe'li bo'lib, yashirin fo'ili Alloh. Salavotga salom duosini qo'shib, duo iborasini to'liq va an'anaviy shaklga keltiradi. Atf qoidasiga ko'ra ma'tuf ma'tufun alayh bilan bir xil grammatik vazifada — fe'l sifatida — turadi.",
          "uz": "salom bo'lsin"
        }
      ]
    },
    {
      "ar": "وَصَلَّى اللَّهُ عَلَى ابْنِهِ إِسْمَاعِيلَ وَسَلَّمَ.",
      "tr": "Allohning salovoti va salomi uning o'g'li Ismoilga bo'lsin.",
      "parts": [
        {
          "w": "وَصَلَّى اللَّهُ",
          "r": "فِعل وَفَاعِل",
          "rc": "tf",
          "e": "وَصَلَّى اللَّهُ oldingi salavot jumlasiga vov atf bilan bog'langan ikkinchi duo tarkibi bo'lib, صَلَّى fe'li va اللَّهُ fo'ilidan iborat. Bu tarkib birinchi salavotga qo'shimcha sifatida Ismoilga ham duo qilinayotganini bildiradi. Duo iborasi rivoyatni ilohiy rahmat va salom bilan yakunlaydi.",
          "uz": "Allohning salovoti bo'lsin"
        },
        {
          "w": "عَلَى ابْنِهِ",
          "r": "جَار وَمَجرُور",
          "rc": "tmt",
          "e": "عَلَى ابْنِهِ jar-majrur tarkibi bo'lib, وَصَلَّى fe'liga mutaalliq. عَلَى yo'nalish bildiruvchi harf jar, ابْنِهِ esa izofa tarkibida jarr holatida kelgan. Ondagi -هِ zamiri Ibrohimga qaytib, salavot uning farzandiga qaratilganini ko'rsatadi.",
          "uz": "o'g'liga"
        },
        {
          "w": "إِسْمَاعِيلَ",
          "r": "بَدَل",
          "rc": "tb",
          "e": "إِسْمَاعِيلَ ابْنِهِ so'zining badali bo'lib, o'rnini bosayotgan ism bilan grammatik muvofiqlikda turadi. Badal qoidasi bo'yicha jarr holatida bo'lishi lozim, ammo gayr munsarif sifatida kasra o'rniga fatha bilan kelgan. «Uning o'g'li» noaniq iborasini to'liq ism bilan oydinlashtiradi.",
          "uz": "Ismoilni"
        },
        {
          "w": "وَسَلَّمَ",
          "r": "فِعل مَعطُوف",
          "rc": "tf",
          "e": "وَسَلَّمَ وَصَلَّىga vov atf bilan bog'langan ikkinchi duo fe'li bo'lib, yashirin fo'ili Alloh. Ismoilga ham salavot bilan birga salom duosini qo'shib, duo iborasini to'liqlashtiradi. Bu so'z bilan butun rivoyat — Ibrohim va Ismoilning buyuk sinovining hikoyasi — ilohiy salom bilan yakunlanadi.",
          "uz": "salom bo'lsin"
        }
      ]
    }
  ],
  "bookId": "qisas"
}
