{
  "وَفَرِحَ": "xursand bo'ldi",
  "الْإِخْوَةُ": "aka-ukalar",
  "كَثِيرًا": "ko'p",
  "لَمَّا أَذِنَ يَعْقُوبُ": "Ya'qub ruxsat berganida",
  "لِيُوسُفَ": "Yusufga",
  "وَذَهَبُوا": "bordilar",
  "إِلَى غَابَةٍ": "o'rmonga",
  "وَأَلْقَوْا": "tashladilar",
  "يُوسُفَ": "Yusufni",
  "فِي بِئْرٍ": "quduqqa",
  "فِي الْغَابَةِ": "o'rmonda",
  "وَلَمْ يَرْحَمُوا": "rahm qilmadilar",
  "يُوسُفَ الصَّغِيرَ": "kichkina Yusufga",
  "يَعْقُوبَ الشَّيْخَ الْكَبِيرَ": "keksa chol Ya'qubga",
  "وَكَانَ يُوسُفُ": "Va Yusuf edi",
  "وَلَدًا صَغِيرًا": "kichkina bola",
  "وَكَانَ قَلْبُهُ": "Va uning qalbi edi",
  "صَغِيرًا": "kichkina",
  "وَكَانَتِ الْبِئْرُ": "Va quduq edi",
  "عَمِيقَةً": "chuqur",
  "مُظْلِمَةً": "qorong'i",
  "وَحِيدًا": "yolg'iz",
  "وَلَكِنَّ اللَّهَ": "Lekin Alloh",
  "بَشَّرَ": "xushxabar berdi",
  "وَقَالَ": "va dedi",
  "لَهُ": "uning",
  "لَا تَحْزَنْ": "g'amgin bo'lma",
  "وَلَا تَخَفْ": "qo'rqma",
  "إِنَّ اللَّهَ": "albatta Alloh",
  "مَعَكَ": "sen bilan",
  "وَسَيَكُونُ": "Va tez orada bo'ladi",
  "لَكَ": "senga",
  "شَأْنٌ": "shan (martaba)",
  "سَيَأْتِي": "keladilar",
  "إِلَيْكَ": "sening oldingga",
  "وَتُخْبِرُهُمْ": "Va ularga xabar berasan",
  "بِمَا": "nima",
  "فَعَلُوهُ": "qilganliklarini",
  "وَلَمَّا": "qachonki",
  "فَرَغُوا": "tugatdilar",
  "مِنْ شَأْنِهِمْ": "o'z ishlaridan",
  "فِي الْبِئْرِ": "Quduqda",
  "اجْتَمَعُوا": "yig'ilishdilar",
  "وَقَالُوا": "va dedilar",
  "مَاذَا": "nimadan",
  "نَقُولُ": "deymiz",
  "لِأَبِينَا": "otamizga",
  "قَالَ": "dedi",
  "بَعْضُهُمْ": "ulardan biri",
  "كَانَ أَبُونَا": "otamiz edi",
  "يَقُولُ": "deydi",
  "أَخَافُ": "qo'rqaman",
  "أَنْ يَأْكُلَهُ": "uni yeb qo'yishidan",
  "الذِّئْبُ": "bo'ri",
  "فَنَقُولُ": "biz deymiz",
  "صَدَقْتَ": "rost aytding",
  "يَا أَبَانَا": "ey otamiz",
  "قَدْ أَكَلَهُ": "uni yeb qo'ydi",
  "وَافَقَ": "rozi bo'ldi",
  "عَلَى ذَلِكَ": "bunga",
  "نَعَمْ": "ha",
  "قَدْ أَكَلَهُ الذِّئْبُ": "Haqiqatan uni bo'ri yedi",
  "بَعْضُ الْإِخْوَانِ": "akallardan biri",
  "وَلَكِنْ": "lekin",
  "مَا": "narsalarni",
  "آيَةُ ذَلِكَ": "buning dalili",
  "قَالُوا": "Dedilar",
  "الدَّمُ": "qon",
  "وَأَخَذَ": "oldi",
  "كَبْشًا": "qo'chqor",
  "وَذَبَحُوهُ": "uni so'yishdi",
  "وَأَخَذُوا": "Va oldilar",
  "قَمِيصَ يُوسُفَ": "Yusufning ko'ylagini",
  "وَصَبَغُوهُ": "uni bo'yashdi",
  "جِدًّا": "juda",
  "الْآنَ": "endi",
  "يُصَدِّقُنَا": "bizga ishonadi",
  "أَبُونَا": "otamiz"
}
